[
  {
    "appid": 1027970,
    "peak_count": -1
  },
  {
    "appid": 1027990,
    "peak_count": 7
  },
  {
    "appid": 1028010,
    "peak_count": -1
  },
  {
    "appid": 1028030,
    "peak_count": -1
  },
  {
    "appid": 1028090,
    "peak_count": 2
  },
  {
    "appid": 102810,
    "peak_count": 44
  },
  {
    "appid": 1028110,
    "peak_count": 4
  },
  {
    "appid": 1028130,
    "peak_count": -1
  },
  {
    "appid": 1028160,
    "peak_count": -1
  },
  {
    "appid": 1028170,
    "peak_count": -1
  },
  {
    "appid": 1028250,
    "peak_count": -1
  },
  {
    "appid": 1028280,
    "peak_count": -1
  },
  {
    "appid": 1028300,
    "peak_count": -1
  },
  {
    "appid": 1028330,
    "peak_count": -1
  },
  {
    "appid": 1028340,
    "peak_count": -1
  },
  {
    "appid": 1028350,
    "peak_count": 70
  },
  {
    "appid": 1028360,
    "peak_count": -1
  },
  {
    "appid": 1028380,
    "peak_count": -1
  },
  {
    "appid": 102840,
    "peak_count": 448
  },
  {
    "appid": 1028410,
    "peak_count": -1
  },
  {
    "appid": 1028460,
    "peak_count": -1
  },
  {
    "appid": 1028470,
    "peak_count": 893
  },
  {
    "appid": 1028480,
    "peak_count": -1
  },
  {
    "appid": 1028490,
    "peak_count": -1
  },
  {
    "appid": 102850,
    "peak_count": 63
  },
  {
    "appid": 1028500,
    "peak_count": 1
  },
  {
    "appid": 1028520,
    "peak_count": -1
  },
  {
    "appid": 1028550,
    "peak_count": -1
  },
  {
    "appid": 1028570,
    "peak_count": 33
  },
  {
    "appid": 1028590,
    "peak_count": 5
  },
  {
    "appid": 1028610,
    "peak_count": -1
  },
  {
    "appid": 1028630,
    "peak_count": 632
  },
  {
    "appid": 1028660,
    "peak_count": -1
  },
  {
    "appid": 1028730,
    "peak_count": -1
  },
  {
    "appid": 1028740,
    "peak_count": -1
  },
  {
    "appid": 1028750,
    "peak_count": 34
  },
  {
    "appid": 1028760,
    "peak_count": 3
  },
  {
    "appid": 1028770,
    "peak_count": -1
  },
  {
    "appid": 1028820,
    "peak_count": -1
  },
  {
    "appid": 1028830,
    "peak_count": -1
  },
  {
    "appid": 1028840,
    "peak_count": -1
  },
  {
    "appid": 1028850,
    "peak_count": -1
  },
  {
    "appid": 1028860,
    "peak_count": 175
  },
  {
    "appid": 1028880,
    "peak_count": -1
  },
  {
    "appid": 1028900,
    "peak_count": -1
  },
  {
    "appid": 1028910,
    "peak_count": 1
  },
  {
    "appid": 1028930,
    "peak_count": -1
  },
  {
    "appid": 1028950,
    "peak_count": -1
  },
  {
    "appid": 1028990,
    "peak_count": 1
  },
  {
    "appid": 1029020,
    "peak_count": -1
  },
  {
    "appid": 1029040,
    "peak_count": -1
  },
  {
    "appid": 1029050,
    "peak_count": -1
  },
  {
    "appid": 1029070,
    "peak_count": -1
  },
  {
    "appid": 1029080,
    "peak_count": 2
  },
  {
    "appid": 1029100,
    "peak_count": 5
  },
  {
    "appid": 1029110,
    "peak_count": -1
  },
  {
    "appid": 1029120,
    "peak_count": -1
  },
  {
    "appid": 1029130,
    "peak_count": 16
  },
  {
    "appid": 1029150,
    "peak_count": 17
  },
  {
    "appid": 1029160,
    "peak_count": -1
  },
  {
    "appid": 1029170,
    "peak_count": -1
  },
  {
    "appid": 1029210,
    "peak_count": 749
  },
  {
    "appid": 1029220,
    "peak_count": -1
  },
  {
    "appid": 1029230,
    "peak_count": -1
  },
  {
    "appid": 1029260,
    "peak_count": -1
  },
  {
    "appid": 1029340,
    "peak_count": 5
  },
  {
    "appid": 1029380,
    "peak_count": -1
  },
  {
    "appid": 1029470,
    "peak_count": -1
  },
  {
    "appid": 1029500,
    "peak_count": 420
  },
  {
    "appid": 1029530,
    "peak_count": -1
  },
  {
    "appid": 1029540,
    "peak_count": -1
  },
  {
    "appid": 1029550,
    "peak_count": 1202
  },
  {
    "appid": 1029560,
    "peak_count": -1
  },
  {
    "appid": 1029570,
    "peak_count": -1
  },
  {
    "appid": 1029630,
    "peak_count": 323
  },
  {
    "appid": 1029640,
    "peak_count": -1
  },
  {
    "appid": 1029650,
    "peak_count": -1
  },
  {
    "appid": 1029660,
    "peak_count": -1
  },
  {
    "appid": 1029690,
    "peak_count": 14794
  },
  {
    "appid": 1029730,
    "peak_count": -1
  },
  {
    "appid": 1029750,
    "peak_count": -1
  },
  {
    "appid": 1029760,
    "peak_count": -1
  },
  {
    "appid": 1029780,
    "peak_count": 14600
  },
  {
    "appid": 1029790,
    "peak_count": -1
  },
  {
    "appid": 1029840,
    "peak_count": -1
  },
  {
    "appid": 1029860,
    "peak_count": 23
  },
  {
    "appid": 1029870,
    "peak_count": -1
  },
  {
    "appid": 1029890,
    "peak_count": -1
  },
  {
    "appid": 1029900,
    "peak_count": -1
  },
  {
    "appid": 1029920,
    "peak_count": -1
  },
  {
    "appid": 1029930,
    "peak_count": -1
  },
  {
    "appid": 1029950,
    "peak_count": -1
  },
  {
    "appid": 1029970,
    "peak_count": -1
  },
  {
    "appid": 1029980,
    "peak_count": 11
  },
  {
    "appid": 1030060,
    "peak_count": -1
  },
  {
    "appid": 1030090,
    "peak_count": -1
  },
  {
    "appid": 1030170,
    "peak_count": 4
  },
  {
    "appid": 1030180,
    "peak_count": 4
  },
  {
    "appid": 1030190,
    "peak_count": -1
  },
  {
    "appid": 1030210,
    "peak_count": 3849
  },
  {
    "appid": 1030240,
    "peak_count": -1
  },
  {
    "appid": 1030310,
    "peak_count": -1
  },
  {
    "appid": 1030330,
    "peak_count": 1
  },
  {
    "appid": 1030350,
    "peak_count": -1
  },
  {
    "appid": 1030360,
    "peak_count": -1
  },
  {
    "appid": 1030380,
    "peak_count": -1
  },
  {
    "appid": 1030410,
    "peak_count": -1
  },
  {
    "appid": 1030430,
    "peak_count": -1
  },
  {
    "appid": 1030470,
    "peak_count": -1
  },
  {
    "appid": 1030530,
    "peak_count": 4
  },
  {
    "appid": 1030580,
    "peak_count": -1
  },
  {
    "appid": 1030730,
    "peak_count": -1
  },
  {
    "appid": 1030760,
    "peak_count": -1
  },
  {
    "appid": 1030830,
    "peak_count": 3818
  },
  {
    "appid": 1030840,
    "peak_count": 36631
  },
  {
    "appid": 1030950,
    "peak_count": 43
  },
  {
    "appid": 1030960,
    "peak_count": 3
  },
  {
    "appid": 1030970,
    "peak_count": -1
  },
  {
    "appid": 1031110,
    "peak_count": -1
  },
  {
    "appid": 1031120,
    "peak_count": 277
  },
  {
    "appid": 1031130,
    "peak_count": -1
  },
  {
    "appid": 1031140,
    "peak_count": 481
  },
  {
    "appid": 1031200,
    "peak_count": -1
  },
  {
    "appid": 1031210,
    "peak_count": -1
  },
  {
    "appid": 1031220,
    "peak_count": -1
  },
  {
    "appid": 1031230,
    "peak_count": -1
  },
  {
    "appid": 1031270,
    "peak_count": 50
  },
  {
    "appid": 1031290,
    "peak_count": -1
  },
  {
    "appid": 1031310,
    "peak_count": -1
  },
  {
    "appid": 1031320,
    "peak_count": -1
  },
  {
    "appid": 1031330,
    "peak_count": -1
  },
  {
    "appid": 1031370,
    "peak_count": -1
  },
  {
    "appid": 1031380,
    "peak_count": -1
  },
  {
    "appid": 1031440,
    "peak_count": -1
  },
  {
    "appid": 1031470,
    "peak_count": 1
  },
  {
    "appid": 1031480,
    "peak_count": 619
  },
  {
    "appid": 1031540,
    "peak_count": -1
  },
  {
    "appid": 1031560,
    "peak_count": -1
  },
  {
    "appid": 1031570,
    "peak_count": -1
  },
  {
    "appid": 1031580,
    "peak_count": 3
  },
  {
    "appid": 1031630,
    "peak_count": 3
  },
  {
    "appid": 1031640,
    "peak_count": 2
  },
  {
    "appid": 1031650,
    "peak_count": -1
  },
  {
    "appid": 1031660,
    "peak_count": 2
  },
  {
    "appid": 1031670,
    "peak_count": -1
  },
  {
    "appid": 1031700,
    "peak_count": -1
  },
  {
    "appid": 1031770,
    "peak_count": -1
  },
  {
    "appid": 1031790,
    "peak_count": -1
  },
  {
    "appid": 1031800,
    "peak_count": -1
  },
  {
    "appid": 1031830,
    "peak_count": -1
  },
  {
    "appid": 1031840,
    "peak_count": 3
  },
  {
    "appid": 1031850,
    "peak_count": -1
  },
  {
    "appid": 1031900,
    "peak_count": -1
  },
  {
    "appid": 1031910,
    "peak_count": -1
  },
  {
    "appid": 1031920,
    "peak_count": 7
  },
  {
    "appid": 1032020,
    "peak_count": -1
  },
  {
    "appid": 1032040,
    "peak_count": -1
  },
  {
    "appid": 1032060,
    "peak_count": -1
  },
  {
    "appid": 1032070,
    "peak_count": -1
  },
  {
    "appid": 1032080,
    "peak_count": -1
  },
  {
    "appid": 1032090,
    "peak_count": -1
  },
  {
    "appid": 1032120,
    "peak_count": 25
  },
  {
    "appid": 1032140,
    "peak_count": -1
  },
  {
    "appid": 1032170,
    "peak_count": -1
  },
  {
    "appid": 1032210,
    "peak_count": -1
  },
  {
    "appid": 1032230,
    "peak_count": -1
  },
  {
    "appid": 1032240,
    "peak_count": -1
  },
  {
    "appid": 1032260,
    "peak_count": 1
  },
  {
    "appid": 1032340,
    "peak_count": -1
  },
  {
    "appid": 1032430,
    "peak_count": 119
  },
  {
    "appid": 1032440,
    "peak_count": -1
  },
  {
    "appid": 1032450,
    "peak_count": -1
  },
  {
    "appid": 1032510,
    "peak_count": -1
  },
  {
    "appid": 1032520,
    "peak_count": 19
  },
  {
    "appid": 1032560,
    "peak_count": 2
  },
  {
    "appid": 1032580,
    "peak_count": -1
  },
  {
    "appid": 1032590,
    "peak_count": -1
  },
  {
    "appid": 1032660,
    "peak_count": 4
  },
  {
    "appid": 1032670,
    "peak_count": -1
  },
  {
    "appid": 1032700,
    "peak_count": 32
  },
  {
    "appid": 1032730,
    "peak_count": -1
  },
  {
    "appid": 1032750,
    "peak_count": -1
  },
  {
    "appid": 1032770,
    "peak_count": 4
  },
  {
    "appid": 1032790,
    "peak_count": 481
  },
  {
    "appid": 1032830,
    "peak_count": 7
  },
  {
    "appid": 1033000,
    "peak_count": 2
  },
  {
    "appid": 1033080,
    "peak_count": 27
  },
  {
    "appid": 1033090,
    "peak_count": 2
  },
  {
    "appid": 1033100,
    "peak_count": -1
  },
  {
    "appid": 1033110,
    "peak_count": -1
  },
  {
    "appid": 1033130,
    "peak_count": -1
  },
  {
    "appid": 1033140,
    "peak_count": 16
  },
  {
    "appid": 1033150,
    "peak_count": -1
  },
  {
    "appid": 1033170,
    "peak_count": -1
  },
  {
    "appid": 1033210,
    "peak_count": -1
  },
  {
    "appid": 1033220,
    "peak_count": 5
  },
  {
    "appid": 1033230,
    "peak_count": -1
  },
  {
    "appid": 1033240,
    "peak_count": -1
  },
  {
    "appid": 1033250,
    "peak_count": 1
  },
  {
    "appid": 1033330,
    "peak_count": -1
  },
  {
    "appid": 1033340,
    "peak_count": -1
  },
  {
    "appid": 1033360,
    "peak_count": -1
  },
  {
    "appid": 1033370,
    "peak_count": 1
  },
  {
    "appid": 1033410,
    "peak_count": -1
  },
  {
    "appid": 1033420,
    "peak_count": 57
  },
  {
    "appid": 1033450,
    "peak_count": -1
  },
  {
    "appid": 1033510,
    "peak_count": -1
  },
  {
    "appid": 1033630,
    "peak_count": 0
  },
  {
    "appid": 1033640,
    "peak_count": -1
  },
  {
    "appid": 1033660,
    "peak_count": -1
  },
  {
    "appid": 1033670,
    "peak_count": 3
  },
  {
    "appid": 1033700,
    "peak_count": 8
  },
  {
    "appid": 1033710,
    "peak_count": -1
  },
  {
    "appid": 1033720,
    "peak_count": 1
  },
  {
    "appid": 1033780,
    "peak_count": -1
  },
  {
    "appid": 1033810,
    "peak_count": 51
  },
  {
    "appid": 1033860,
    "peak_count": -1
  },
  {
    "appid": 1033880,
    "peak_count": 10
  },
  {
    "appid": 1033930,
    "peak_count": -1
  },
  {
    "appid": 1033950,
    "peak_count": 133
  },
  {
    "appid": 1034030,
    "peak_count": -1
  },
  {
    "appid": 1034120,
    "peak_count": -1
  },
  {
    "appid": 1034130,
    "peak_count": 1
  },
  {
    "appid": 1034150,
    "peak_count": -1
  },
  {
    "appid": 1034160,
    "peak_count": -1
  },
  {
    "appid": 1034200,
    "peak_count": 13
  },
  {
    "appid": 1034230,
    "peak_count": -1
  },
  {
    "appid": 1034240,
    "peak_count": -1
  },
  {
    "appid": 1034250,
    "peak_count": 5
  },
  {
    "appid": 1034260,
    "peak_count": -1
  },
  {
    "appid": 1034270,
    "peak_count": -1
  },
  {
    "appid": 1034280,
    "peak_count": 3
  },
  {
    "appid": 1034370,
    "peak_count": -1
  },
  {
    "appid": 1034380,
    "peak_count": -1
  },
  {
    "appid": 1034390,
    "peak_count": -1
  },
  {
    "appid": 1034400,
    "peak_count": 8
  },
  {
    "appid": 1034410,
    "peak_count": -1
  },
  {
    "appid": 1034440,
    "peak_count": -1
  },
  {
    "appid": 1034540,
    "peak_count": 10
  },
  {
    "appid": 1034560,
    "peak_count": 6
  },
  {
    "appid": 1034610,
    "peak_count": -1
  },
  {
    "appid": 1034700,
    "peak_count": 95
  },
  {
    "appid": 1034740,
    "peak_count": 8
  },
  {
    "appid": 1034750,
    "peak_count": -1
  },
  {
    "appid": 1034820,
    "peak_count": -1
  },
  {
    "appid": 1034830,
    "peak_count": 0
  },
  {
    "appid": 1034850,
    "peak_count": -1
  },
  {
    "appid": 1034860,
    "peak_count": 292
  },
  {
    "appid": 1034870,
    "peak_count": -1
  },
  {
    "appid": 1034880,
    "peak_count": -1
  },
  {
    "appid": 1034890,
    "peak_count": 12
  },
  {
    "appid": 1034900,
    "peak_count": 87
  },
  {
    "appid": 1034920,
    "peak_count": -1
  },
  {
    "appid": 1034930,
    "peak_count": 4
  },
  {
    "appid": 1034940,
    "peak_count": 48
  },
  {
    "appid": 1034950,
    "peak_count": -1
  },
  {
    "appid": 1035050,
    "peak_count": -1
  },
  {
    "appid": 1035110,
    "peak_count": -1
  },
  {
    "appid": 1035180,
    "peak_count": -1
  },
  {
    "appid": 1035190,
    "peak_count": -1
  },
  {
    "appid": 1035260,
    "peak_count": 1
  },
  {
    "appid": 1035270,
    "peak_count": -1
  },
  {
    "appid": 1035280,
    "peak_count": -1
  },
  {
    "appid": 1035300,
    "peak_count": -1
  },
  {
    "appid": 1035310,
    "peak_count": -1
  },
  {
    "appid": 1035320,
    "peak_count": -1
  },
  {
    "appid": 1035340,
    "peak_count": -1
  },
  {
    "appid": 1035410,
    "peak_count": -1
  },
  {
    "appid": 1035430,
    "peak_count": 1
  },
  {
    "appid": 1035470,
    "peak_count": -1
  },
  {
    "appid": 1035490,
    "peak_count": -1
  },
  {
    "appid": 1035500,
    "peak_count": -1
  },
  {
    "appid": 1035510,
    "peak_count": 1063
  },
  {
    "appid": 1035530,
    "peak_count": 2
  },
  {
    "appid": 1035550,
    "peak_count": 2
  },
  {
    "appid": 1035560,
    "peak_count": -1
  },
  {
    "appid": 1035600,
    "peak_count": 1
  },
  {
    "appid": 1035610,
    "peak_count": 352
  },
  {
    "appid": 1035660,
    "peak_count": -1
  },
  {
    "appid": 1035690,
    "peak_count": -1
  },
  {
    "appid": 1035700,
    "peak_count": -1
  },
  {
    "appid": 1035750,
    "peak_count": -1
  },
  {
    "appid": 1035770,
    "peak_count": 12
  },
  {
    "appid": 1035790,
    "peak_count": 4
  },
  {
    "appid": 1035800,
    "peak_count": -1
  },
  {
    "appid": 1035830,
    "peak_count": -1
  },
  {
    "appid": 1035850,
    "peak_count": -1
  },
  {
    "appid": 1035860,
    "peak_count": 2
  },
  {
    "appid": 1035880,
    "peak_count": -1
  },
  {
    "appid": 1035890,
    "peak_count": -1
  },
  {
    "appid": 1035900,
    "peak_count": -1
  },
  {
    "appid": 1035920,
    "peak_count": 2
  },
  {
    "appid": 1035930,
    "peak_count": 32027
  },
  {
    "appid": 1035950,
    "peak_count": 6
  },
  {
    "appid": 1035960,
    "peak_count": 1
  },
  {
    "appid": 1035990,
    "peak_count": 132
  },
  {
    "appid": 1036000,
    "peak_count": 2
  },
  {
    "appid": 1036010,
    "peak_count": 2
  },
  {
    "appid": 1036030,
    "peak_count": -1
  },
  {
    "appid": 1036120,
    "peak_count": 9
  },
  {
    "appid": 1036200,
    "peak_count": 3
  },
  {
    "appid": 1036260,
    "peak_count": -1
  },
  {
    "appid": 1036270,
    "peak_count": -1
  },
  {
    "appid": 1036320,
    "peak_count": -1
  },
  {
    "appid": 1036330,
    "peak_count": -1
  },
  {
    "appid": 1036340,
    "peak_count": 64
  },
  {
    "appid": 1036370,
    "peak_count": -1
  },
  {
    "appid": 1036400,
    "peak_count": 1
  },
  {
    "appid": 1036420,
    "peak_count": -1
  },
  {
    "appid": 1036440,
    "peak_count": 116
  },
  {
    "appid": 1036460,
    "peak_count": -1
  },
  {
    "appid": 1036490,
    "peak_count": 2
  },
  {
    "appid": 1036530,
    "peak_count": -1
  },
  {
    "appid": 1036540,
    "peak_count": 1
  },
  {
    "appid": 1036550,
    "peak_count": 0
  },
  {
    "appid": 1036580,
    "peak_count": -1
  },
  {
    "appid": 1036600,
    "peak_count": -1
  },
  {
    "appid": 1036620,
    "peak_count": -1
  },
  {
    "appid": 1036640,
    "peak_count": 240
  },
  {
    "appid": 1036660,
    "peak_count": -1
  },
  {
    "appid": 1036700,
    "peak_count": 13
  },
  {
    "appid": 1036740,
    "peak_count": 722
  },
  {
    "appid": 1036780,
    "peak_count": -1
  },
  {
    "appid": 1036800,
    "peak_count": -1
  },
  {
    "appid": 1036820,
    "peak_count": -1
  },
  {
    "appid": 1036840,
    "peak_count": -1
  },
  {
    "appid": 1036850,
    "peak_count": -1
  },
  {
    "appid": 1036870,
    "peak_count": -1
  },
  {
    "appid": 1036890,
    "peak_count": 1621
  },
  {
    "appid": 1036900,
    "peak_count": -1
  },
  {
    "appid": 1036920,
    "peak_count": 2
  },
  {
    "appid": 1036930,
    "peak_count": 42
  },
  {
    "appid": 1036950,
    "peak_count": 220
  },
  {
    "appid": 1036960,
    "peak_count": 20
  },
  {
    "appid": 1036970,
    "peak_count": 4
  },
  {
    "appid": 1036980,
    "peak_count": 10
  },
  {
    "appid": 1036990,
    "peak_count": -1
  },
  {
    "appid": 1037000,
    "peak_count": -1
  },
  {
    "appid": 1037010,
    "peak_count": -1
  },
  {
    "appid": 1037020,
    "peak_count": 325
  },
  {
    "appid": 1037080,
    "peak_count": -1
  },
  {
    "appid": 1037090,
    "peak_count": -1
  },
  {
    "appid": 1037100,
    "peak_count": -1
  },
  {
    "appid": 1037110,
    "peak_count": -1
  },
  {
    "appid": 1037130,
    "peak_count": 431
  },
  {
    "appid": 1037140,
    "peak_count": -1
  },
  {
    "appid": 1037190,
    "peak_count": 15
  },
  {
    "appid": 1037260,
    "peak_count": -1
  },
  {
    "appid": 1037270,
    "peak_count": -1
  },
  {
    "appid": 1037330,
    "peak_count": 1
  },
  {
    "appid": 1037340,
    "peak_count": -1
  },
  {
    "appid": 1037350,
    "peak_count": -1
  },
  {
    "appid": 1037410,
    "peak_count": 40
  },
  {
    "appid": 1037430,
    "peak_count": -1
  },
  {
    "appid": 1037460,
    "peak_count": -1
  },
  {
    "appid": 1037480,
    "peak_count": 13
  },
  {
    "appid": 1037560,
    "peak_count": 7
  },
  {
    "appid": 1037570,
    "peak_count": -1
  },
  {
    "appid": 1037590,
    "peak_count": -1
  },
  {
    "appid": 1037600,
    "peak_count": -1
  },
  {
    "appid": 1037690,
    "peak_count": 5
  },
  {
    "appid": 1037750,
    "peak_count": -1
  },
  {
    "appid": 1037760,
    "peak_count": -1
  },
  {
    "appid": 1037820,
    "peak_count": -1
  },
  {
    "appid": 1037830,
    "peak_count": -1
  },
  {
    "appid": 1037840,
    "peak_count": -1
  },
  {
    "appid": 1037850,
    "peak_count": 1
  },
  {
    "appid": 1037910,
    "peak_count": 58
  },
  {
    "appid": 1037930,
    "peak_count": 1
  },
  {
    "appid": 1037940,
    "peak_count": 18
  },
  {
    "appid": 1037950,
    "peak_count": 6
  },
  {
    "appid": 1037970,
    "peak_count": -1
  },
  {
    "appid": 1038000,
    "peak_count": 7
  },
  {
    "appid": 1038070,
    "peak_count": -1
  },
  {
    "appid": 1038100,
    "peak_count": -1
  },
  {
    "appid": 1038120,
    "peak_count": -1
  },
  {
    "appid": 1038240,
    "peak_count": -1
  },
  {
    "appid": 1038250,
    "peak_count": 1200
  },
  {
    "appid": 1038280,
    "peak_count": 32
  },
  {
    "appid": 1038300,
    "peak_count": 22
  },
  {
    "appid": 1038370,
    "peak_count": 1743
  },
  {
    "appid": 1038380,
    "peak_count": -1
  },
  {
    "appid": 1038410,
    "peak_count": -1
  },
  {
    "appid": 1038430,
    "peak_count": -1
  },
  {
    "appid": 1038440,
    "peak_count": 2
  },
  {
    "appid": 1038450,
    "peak_count": 800
  },
  {
    "appid": 1038620,
    "peak_count": 12
  },
  {
    "appid": 1038630,
    "peak_count": 6
  },
  {
    "appid": 1038640,
    "peak_count": -1
  },
  {
    "appid": 1038650,
    "peak_count": 5
  },
  {
    "appid": 1038670,
    "peak_count": 5
  },
  {
    "appid": 1038680,
    "peak_count": -1
  },
  {
    "appid": 1038740,
    "peak_count": 393
  },
  {
    "appid": 1038810,
    "peak_count": 85
  },
  {
    "appid": 1038820,
    "peak_count": 41
  },
  {
    "appid": 1038830,
    "peak_count": -1
  },
  {
    "appid": 1038850,
    "peak_count": -1
  },
  {
    "appid": 1039040,
    "peak_count": -1
  },
  {
    "appid": 1039060,
    "peak_count": -1
  },
  {
    "appid": 1039080,
    "peak_count": -1
  },
  {
    "appid": 1039100,
    "peak_count": -1
  },
  {
    "appid": 1039110,
    "peak_count": -1
  },
  {
    "appid": 1039200,
    "peak_count": -1
  },
  {
    "appid": 1039310,
    "peak_count": -1
  },
  {
    "appid": 1039330,
    "peak_count": -1
  },
  {
    "appid": 1039350,
    "peak_count": -1
  },
  {
    "appid": 1039360,
    "peak_count": 47
  },
  {
    "appid": 1039370,
    "peak_count": -1
  },
  {
    "appid": 1039380,
    "peak_count": -1
  },
  {
    "appid": 1039430,
    "peak_count": -1
  },
  {
    "appid": 1039470,
    "peak_count": -1
  },
  {
    "appid": 1039550,
    "peak_count": -1
  },
  {
    "appid": 1039560,
    "peak_count": 4
  },
  {
    "appid": 1039580,
    "peak_count": 4
  },
  {
    "appid": 1039590,
    "peak_count": -1
  },
  {
    "appid": 1039800,
    "peak_count": -1
  },
  {
    "appid": 1039860,
    "peak_count": -1
  },
  {
    "appid": 1039870,
    "peak_count": -1
  },
  {
    "appid": 1039880,
    "peak_count": 142
  },
  {
    "appid": 1039890,
    "peak_count": 501
  },
  {
    "appid": 1039910,
    "peak_count": 2
  },
  {
    "appid": 1039960,
    "peak_count": 77
  },
  {
    "appid": 104000,
    "peak_count": -1
  },
  {
    "appid": 1040000,
    "peak_count": -1
  },
  {
    "appid": 1040070,
    "peak_count": 625
  },
  {
    "appid": 1040080,
    "peak_count": -1
  },
  {
    "appid": 1040150,
    "peak_count": -1
  },
  {
    "appid": 1040190,
    "peak_count": -1
  },
  {
    "appid": 104020,
    "peak_count": -1
  },
  {
    "appid": 1040230,
    "peak_count": 3043
  },
  {
    "appid": 1040310,
    "peak_count": -1
  },
  {
    "appid": 1040370,
    "peak_count": -1
  },
  {
    "appid": 1040390,
    "peak_count": 7
  },
  {
    "appid": 1040420,
    "peak_count": 1111
  },
  {
    "appid": 1040430,
    "peak_count": 164
  },
  {
    "appid": 1040460,
    "peak_count": 96
  },
  {
    "appid": 1040480,
    "peak_count": 0
  },
  {
    "appid": 1040490,
    "peak_count": 28
  },
  {
    "appid": 1040550,
    "peak_count": 59
  },
  {
    "appid": 1040590,
    "peak_count": -1
  },
  {
    "appid": 1040610,
    "peak_count": 2
  },
  {
    "appid": 1040620,
    "peak_count": -1
  },
  {
    "appid": 1040630,
    "peak_count": -1
  },
  {
    "appid": 1040720,
    "peak_count": -1
  },
  {
    "appid": 1040730,
    "peak_count": 110
  },
  {
    "appid": 1040740,
    "peak_count": -1
  },
  {
    "appid": 1040750,
    "peak_count": -1
  },
  {
    "appid": 1040810,
    "peak_count": -1
  },
  {
    "appid": 1040820,
    "peak_count": -1
  },
  {
    "appid": 1040890,
    "peak_count": 3
  },
  {
    "appid": 1040900,
    "peak_count": -1
  },
  {
    "appid": 1040910,
    "peak_count": -1
  },
  {
    "appid": 1040940,
    "peak_count": -1
  },
  {
    "appid": 104100,
    "peak_count": -1
  },
  {
    "appid": 1041060,
    "peak_count": 8
  },
  {
    "appid": 1041070,
    "peak_count": 0
  },
  {
    "appid": 1041100,
    "peak_count": -1
  },
  {
    "appid": 1041130,
    "peak_count": -1
  },
  {
    "appid": 1041140,
    "peak_count": -1
  },
  {
    "appid": 1041160,
    "peak_count": -1
  },
  {
    "appid": 1041210,
    "peak_count": -1
  },
  {
    "appid": 1041270,
    "peak_count": 7
  },
  {
    "appid": 1041300,
    "peak_count": -1
  },
  {
    "appid": 1041320,
    "peak_count": 6216
  },
  {
    "appid": 1041330,
    "peak_count": -1
  },
  {
    "appid": 1041390,
    "peak_count": -1
  },
  {
    "appid": 1041400,
    "peak_count": -1
  },
  {
    "appid": 1041450,
    "peak_count": -1
  },
  {
    "appid": 1041500,
    "peak_count": -1
  },
  {
    "appid": 1041520,
    "peak_count": -1
  },
  {
    "appid": 1041650,
    "peak_count": -1
  },
  {
    "appid": 1041660,
    "peak_count": -1
  },
  {
    "appid": 1041670,
    "peak_count": 12
  },
  {
    "appid": 1041690,
    "peak_count": 12
  },
  {
    "appid": 1041710,
    "peak_count": 130
  },
  {
    "appid": 1041720,
    "peak_count": 6219
  },
  {
    "appid": 1041760,
    "peak_count": 5
  },
  {
    "appid": 1041780,
    "peak_count": -1
  },
  {
    "appid": 1041840,
    "peak_count": 121
  },
  {
    "appid": 1041890,
    "peak_count": -1
  },
  {
    "appid": 1041920,
    "peak_count": 38
  },
  {
    "appid": 1041940,
    "peak_count": -1
  },
  {
    "appid": 104200,
    "peak_count": 1339
  },
  {
    "appid": 1042010,
    "peak_count": -1
  },
  {
    "appid": 1042030,
    "peak_count": -1
  },
  {
    "appid": 1042090,
    "peak_count": 1
  },
  {
    "appid": 1042100,
    "peak_count": -1
  },
  {
    "appid": 1042110,
    "peak_count": -1
  },
  {
    "appid": 1042130,
    "peak_count": 2
  },
  {
    "appid": 1042150,
    "peak_count": -1
  },
  {
    "appid": 1042160,
    "peak_count": -1
  },
  {
    "appid": 1042170,
    "peak_count": 33
  },
  {
    "appid": 1042210,
    "peak_count": -1
  },
  {
    "appid": 1042230,
    "peak_count": -1
  },
  {
    "appid": 1042290,
    "peak_count": -1
  },
  {
    "appid": 1042310,
    "peak_count": -1
  },
  {
    "appid": 1042330,
    "peak_count": -1
  },
  {
    "appid": 1042380,
    "peak_count": 478
  },
  {
    "appid": 1042460,
    "peak_count": -1
  },
  {
    "appid": 1042490,
    "peak_count": 191
  },
  {
    "appid": 1042530,
    "peak_count": 43
  },
  {
    "appid": 1042550,
    "peak_count": 2220
  },
  {
    "appid": 1042560,
    "peak_count": -1
  },
  {
    "appid": 1042570,
    "peak_count": 3
  },
  {
    "appid": 1042590,
    "peak_count": 9
  },
  {
    "appid": 1042670,
    "peak_count": 385
  },
  {
    "appid": 1042750,
    "peak_count": 5
  },
  {
    "appid": 1042780,
    "peak_count": 1614
  },
  {
    "appid": 1042800,
    "peak_count": 1290
  },
  {
    "appid": 1042820,
    "peak_count": 3
  },
  {
    "appid": 1042860,
    "peak_count": 0
  },
  {
    "appid": 1042880,
    "peak_count": -1
  },
  {
    "appid": 1042900,
    "peak_count": -1
  },
  {
    "appid": 1042910,
    "peak_count": -1
  },
  {
    "appid": 1042930,
    "peak_count": -1
  },
  {
    "appid": 1042960,
    "peak_count": -1
  },
  {
    "appid": 1042990,
    "peak_count": -1
  },
  {
    "appid": 1043000,
    "peak_count": 4
  },
  {
    "appid": 1043020,
    "peak_count": 1
  },
  {
    "appid": 1043030,
    "peak_count": 1
  },
  {
    "appid": 1043040,
    "peak_count": -1
  },
  {
    "appid": 1043060,
    "peak_count": -1
  },
  {
    "appid": 1043120,
    "peak_count": -1
  },
  {
    "appid": 1043130,
    "peak_count": -1
  },
  {
    "appid": 1043140,
    "peak_count": -1
  },
  {
    "appid": 1043150,
    "peak_count": -1
  },
  {
    "appid": 1043160,
    "peak_count": 1
  },
  {
    "appid": 1043180,
    "peak_count": 637
  },
  {
    "appid": 1043200,
    "peak_count": -1
  },
  {
    "appid": 1043230,
    "peak_count": 18
  },
  {
    "appid": 1043240,
    "peak_count": -1
  },
  {
    "appid": 1043250,
    "peak_count": -1
  },
  {
    "appid": 1043260,
    "peak_count": 1236
  },
  {
    "appid": 1043340,
    "peak_count": 92
  },
  {
    "appid": 1043350,
    "peak_count": -1
  },
  {
    "appid": 1043360,
    "peak_count": -1
  },
  {
    "appid": 1043370,
    "peak_count": -1
  },
  {
    "appid": 1043380,
    "peak_count": -1
  },
  {
    "appid": 1043390,
    "peak_count": 359
  },
  {
    "appid": 1043430,
    "peak_count": 32
  },
  {
    "appid": 1043470,
    "peak_count": -1
  },
  {
    "appid": 1043480,
    "peak_count": -1
  },
  {
    "appid": 1043500,
    "peak_count": 12
  },
  {
    "appid": 1043510,
    "peak_count": 2
  },
  {
    "appid": 1043560,
    "peak_count": 1
  },
  {
    "appid": 1043580,
    "peak_count": 2
  },
  {
    "appid": 1043610,
    "peak_count": 2
  },
  {
    "appid": 1043690,
    "peak_count": -1
  },
  {
    "appid": 1043710,
    "peak_count": -1
  },
  {
    "appid": 1043760,
    "peak_count": -1
  },
  {
    "appid": 1043790,
    "peak_count": -1
  },
  {
    "appid": 1043860,
    "peak_count": -1
  },
  {
    "appid": 1043870,
    "peak_count": -1
  },
  {
    "appid": 1043890,
    "peak_count": 3
  },
  {
    "appid": 1044020,
    "peak_count": -1
  },
  {
    "appid": 1044030,
    "peak_count": -1
  },
  {
    "appid": 1044040,
    "peak_count": -1
  },
  {
    "appid": 1044070,
    "peak_count": 1
  },
  {
    "appid": 1044110,
    "peak_count": -1
  },
  {
    "appid": 1044130,
    "peak_count": -1
  },
  {
    "appid": 1044170,
    "peak_count": -1
  },
  {
    "appid": 1044200,
    "peak_count": 884
  },
  {
    "appid": 1044210,
    "peak_count": 11
  },
  {
    "appid": 1044220,
    "peak_count": -1
  },
  {
    "appid": 1044300,
    "peak_count": 0
  },
  {
    "appid": 1044340,
    "peak_count": 26
  },
  {
    "appid": 1044350,
    "peak_count": -1
  },
  {
    "appid": 1044410,
    "peak_count": -1
  },
  {
    "appid": 1044450,
    "peak_count": -1
  },
  {
    "appid": 1044460,
    "peak_count": 0
  },
  {
    "appid": 1044480,
    "peak_count": 4
  },
  {
    "appid": 1044620,
    "peak_count": 447
  },
  {
    "appid": 1044630,
    "peak_count": -1
  },
  {
    "appid": 1044640,
    "peak_count": 9
  },
  {
    "appid": 1044720,
    "peak_count": 24874
  },
  {
    "appid": 1044730,
    "peak_count": -1
  },
  {
    "appid": 1044750,
    "peak_count": -1
  },
  {
    "appid": 1044760,
    "peak_count": 6
  },
  {
    "appid": 1044770,
    "peak_count": 11
  },
  {
    "appid": 1044790,
    "peak_count": -1
  },
  {
    "appid": 1044800,
    "peak_count": 1
  },
  {
    "appid": 1044840,
    "peak_count": -1
  },
  {
    "appid": 1044870,
    "peak_count": -1
  },
  {
    "appid": 1044900,
    "peak_count": -1
  },
  {
    "appid": 1044920,
    "peak_count": -1
  },
  {
    "appid": 1044930,
    "peak_count": -1
  },
  {
    "appid": 1044950,
    "peak_count": -1
  },
  {
    "appid": 1044980,
    "peak_count": 536
  },
  {
    "appid": 1045010,
    "peak_count": -1
  },
  {
    "appid": 1045020,
    "peak_count": -1
  },
  {
    "appid": 1045060,
    "peak_count": 7
  },
  {
    "appid": 1045070,
    "peak_count": -1
  },
  {
    "appid": 1045080,
    "peak_count": 49
  },
  {
    "appid": 1045110,
    "peak_count": -1
  },
  {
    "appid": 1045120,
    "peak_count": -1
  },
  {
    "appid": 1045130,
    "peak_count": 1
  },
  {
    "appid": 1045140,
    "peak_count": -1
  },
  {
    "appid": 1045150,
    "peak_count": -1
  },
  {
    "appid": 1045180,
    "peak_count": -1
  },
  {
    "appid": 1045220,
    "peak_count": -1
  },
  {
    "appid": 1045280,
    "peak_count": -1
  },
  {
    "appid": 1045300,
    "peak_count": -1
  },
  {
    "appid": 1045310,
    "peak_count": 3
  },
  {
    "appid": 1045390,
    "peak_count": -1
  },
  {
    "appid": 1045400,
    "peak_count": -1
  },
  {
    "appid": 1045430,
    "peak_count": -1
  },
  {
    "appid": 1045510,
    "peak_count": -1
  },
  {
    "appid": 1045530,
    "peak_count": -1
  },
  {
    "appid": 1045580,
    "peak_count": -1
  },
  {
    "appid": 1045590,
    "peak_count": -1
  },
  {
    "appid": 1045610,
    "peak_count": 255
  },
  {
    "appid": 1045620,
    "peak_count": 511
  },
  {
    "appid": 1045650,
    "peak_count": 9
  },
  {
    "appid": 1045680,
    "peak_count": 18
  },
  {
    "appid": 1045720,
    "peak_count": 241
  },
  {
    "appid": 1045740,
    "peak_count": -1
  },
  {
    "appid": 1045850,
    "peak_count": -1
  },
  {
    "appid": 1045900,
    "peak_count": -1
  },
  {
    "appid": 10460,
    "peak_count": -1
  },
  {
    "appid": 104600,
    "peak_count": 54
  },
  {
    "appid": 1046030,
    "peak_count": 1761
  },
  {
    "appid": 1046060,
    "peak_count": -1
  },
  {
    "appid": 1046070,
    "peak_count": -1
  },
  {
    "appid": 1046110,
    "peak_count": 1
  },
  {
    "appid": 1046130,
    "peak_count": -1
  },
  {
    "appid": 1046140,
    "peak_count": -1
  },
  {
    "appid": 1046210,
    "peak_count": 2
  },
  {
    "appid": 1046240,
    "peak_count": -1
  },
  {
    "appid": 1046300,
    "peak_count": 249
  },
  {
    "appid": 1046330,
    "peak_count": -1
  },
  {
    "appid": 1046350,
    "peak_count": 1
  },
  {
    "appid": 1046370,
    "peak_count": -1
  },
  {
    "appid": 1046470,
    "peak_count": -1
  },
  {
    "appid": 1046490,
    "peak_count": -1
  },
  {
    "appid": 1046530,
    "peak_count": -1
  },
  {
    "appid": 1046560,
    "peak_count": -1
  },
  {
    "appid": 1046570,
    "peak_count": -1
  },
  {
    "appid": 1046600,
    "peak_count": 17
  },
  {
    "appid": 1046610,
    "peak_count": 2
  },
  {
    "appid": 1046630,
    "peak_count": -1
  },
  {
    "appid": 1046660,
    "peak_count": 287
  },
  {
    "appid": 1046670,
    "peak_count": 3
  },
  {
    "appid": 1046740,
    "peak_count": -1
  },
  {
    "appid": 1046750,
    "peak_count": 2
  },
  {
    "appid": 1046770,
    "peak_count": 10
  },
  {
    "appid": 1046790,
    "peak_count": 74
  },
  {
    "appid": 1046820,
    "peak_count": 149
  },
  {
    "appid": 1046910,
    "peak_count": -1
  },
  {
    "appid": 1046930,
    "peak_count": 202254
  },
  {
    "appid": 1046980,
    "peak_count": -1
  },
  {
    "appid": 1047010,
    "peak_count": 46
  },
  {
    "appid": 1047020,
    "peak_count": -1
  },
  {
    "appid": 1047090,
    "peak_count": -1
  },
  {
    "appid": 1047120,
    "peak_count": 4
  },
  {
    "appid": 1047140,
    "peak_count": 3
  },
  {
    "appid": 1047160,
    "peak_count": 5
  },
  {
    "appid": 1047170,
    "peak_count": -1
  },
  {
    "appid": 1047190,
    "peak_count": 3
  },
  {
    "appid": 1047220,
    "peak_count": 25
  },
  {
    "appid": 1047240,
    "peak_count": -1
  },
  {
    "appid": 1047340,
    "peak_count": -1
  },
  {
    "appid": 1047350,
    "peak_count": -1
  },
  {
    "appid": 1047380,
    "peak_count": -1
  },
  {
    "appid": 1047410,
    "peak_count": -1
  },
  {
    "appid": 1047430,
    "peak_count": -1
  },
  {
    "appid": 1047440,
    "peak_count": 874
  },
  {
    "appid": 1047480,
    "peak_count": 47
  },
  {
    "appid": 1047580,
    "peak_count": -1
  },
  {
    "appid": 1047620,
    "peak_count": -1
  },
  {
    "appid": 1047640,
    "peak_count": -1
  },
  {
    "appid": 1047720,
    "peak_count": -1
  },
  {
    "appid": 1047750,
    "peak_count": -1
  },
  {
    "appid": 1047780,
    "peak_count": -1
  },
  {
    "appid": 1047800,
    "peak_count": -1
  },
  {
    "appid": 1047810,
    "peak_count": -1
  },
  {
    "appid": 1047840,
    "peak_count": 0
  },
  {
    "appid": 1047850,
    "peak_count": -1
  },
  {
    "appid": 1047860,
    "peak_count": -1
  },
  {
    "appid": 1047870,
    "peak_count": -1
  },
  {
    "appid": 1047910,
    "peak_count": -1
  },
  {
    "appid": 1047930,
    "peak_count": -1
  },
  {
    "appid": 1047950,
    "peak_count": -1
  },
  {
    "appid": 1048000,
    "peak_count": -1
  },
  {
    "appid": 1048020,
    "peak_count": -1
  },
  {
    "appid": 1048040,
    "peak_count": -1
  },
  {
    "appid": 1048080,
    "peak_count": -1
  },
  {
    "appid": 1048090,
    "peak_count": 2
  },
  {
    "appid": 1048100,
    "peak_count": 1477
  },
  {
    "appid": 1048260,
    "peak_count": -1
  },
  {
    "appid": 1048270,
    "peak_count": -1
  },
  {
    "appid": 1048280,
    "peak_count": -1
  },
  {
    "appid": 1048300,
    "peak_count": 11
  },
  {
    "appid": 1048320,
    "peak_count": -1
  },
  {
    "appid": 1048350,
    "peak_count": 500
  },
  {
    "appid": 1048410,
    "peak_count": -1
  },
  {
    "appid": 1048420,
    "peak_count": -1
  },
  {
    "appid": 1048470,
    "peak_count": 3
  },
  {
    "appid": 1048530,
    "peak_count": -1
  },
  {
    "appid": 1048540,
    "peak_count": 795
  },
  {
    "appid": 1048560,
    "peak_count": 5
  },
  {
    "appid": 1048570,
    "peak_count": -1
  },
  {
    "appid": 1048580,
    "peak_count": 6
  },
  {
    "appid": 1048600,
    "peak_count": -1
  },
  {
    "appid": 1048640,
    "peak_count": -1
  },
  {
    "appid": 1048660,
    "peak_count": 125
  },
  {
    "appid": 1048690,
    "peak_count": -1
  },
  {
    "appid": 1048740,
    "peak_count": -1
  },
  {
    "appid": 1048790,
    "peak_count": -1
  },
  {
    "appid": 1048830,
    "peak_count": 68
  },
  {
    "appid": 1048850,
    "peak_count": -1
  },
  {
    "appid": 1048860,
    "peak_count": 4
  },
  {
    "appid": 1048880,
    "peak_count": -1
  },
  {
    "appid": 1048900,
    "peak_count": 8
  },
  {
    "appid": 1048920,
    "peak_count": 6
  },
  {
    "appid": 1048950,
    "peak_count": -1
  },
  {
    "appid": 1048960,
    "peak_count": -1
  },
  {
    "appid": 104900,
    "peak_count": 7876
  },
  {
    "appid": 1049000,
    "peak_count": -1
  },
  {
    "appid": 1049010,
    "peak_count": -1
  },
  {
    "appid": 1049030,
    "peak_count": -1
  },
  {
    "appid": 1049040,
    "peak_count": -1
  },
  {
    "appid": 1049070,
    "peak_count": -1
  },
  {
    "appid": 1049080,
    "peak_count": 1
  },
  {
    "appid": 1049090,
    "peak_count": -1
  },
  {
    "appid": 1049100,
    "peak_count": 384
  },
  {
    "appid": 1049130,
    "peak_count": -1
  },
  {
    "appid": 1049140,
    "peak_count": -1
  },
  {
    "appid": 1049220,
    "peak_count": 8
  },
  {
    "appid": 1049230,
    "peak_count": 0
  },
  {
    "appid": 1049270,
    "peak_count": -1
  },
  {
    "appid": 1049280,
    "peak_count": 120
  },
  {
    "appid": 1049310,
    "peak_count": 2
  },
  {
    "appid": 1049320,
    "peak_count": 476
  },
  {
    "appid": 1049360,
    "peak_count": 10
  },
  {
    "appid": 1049370,
    "peak_count": 2
  },
  {
    "appid": 1049380,
    "peak_count": -1
  },
  {
    "appid": 1049400,
    "peak_count": 12
  },
  {
    "appid": 1049410,
    "peak_count": 1255
  },
  {
    "appid": 1049420,
    "peak_count": -1
  },
  {
    "appid": 1049490,
    "peak_count": 2
  },
  {
    "appid": 1049510,
    "peak_count": -1
  },
  {
    "appid": 1049530,
    "peak_count": -1
  },
  {
    "appid": 1049560,
    "peak_count": 2
  },
  {
    "appid": 1049570,
    "peak_count": 3
  },
  {
    "appid": 1049590,
    "peak_count": 52288
  },
  {
    "appid": 1049640,
    "peak_count": -1
  },
  {
    "appid": 1049660,
    "peak_count": 263
  },
  {
    "appid": 1049670,
    "peak_count": -1
  },
  {
    "appid": 1049680,
    "peak_count": -1
  },
  {
    "appid": 1049690,
    "peak_count": -1
  },
  {
    "appid": 1049710,
    "peak_count": -1
  },
  {
    "appid": 1049720,
    "peak_count": 1
  },
  {
    "appid": 1049730,
    "peak_count": -1
  },
  {
    "appid": 1049800,
    "peak_count": 1138
  },
  {
    "appid": 1049820,
    "peak_count": -1
  },
  {
    "appid": 1049840,
    "peak_count": -1
  },
  {
    "appid": 1049850,
    "peak_count": 74
  },
  {
    "appid": 1049870,
    "peak_count": -1
  },
  {
    "appid": 1049880,
    "peak_count": 31
  },
  {
    "appid": 1049890,
    "peak_count": 3695
  },
  {
    "appid": 1049910,
    "peak_count": -1
  },
  {
    "appid": 1049930,
    "peak_count": -1
  },
  {
    "appid": 1049950,
    "peak_count": -1
  },
  {
    "appid": 10500,
    "peak_count": 10479
  },
  {
    "appid": 105000,
    "peak_count": 173
  },
  {
    "appid": 1050000,
    "peak_count": -1
  },
  {
    "appid": 1050010,
    "peak_count": -1
  },
  {
    "appid": 1050080,
    "peak_count": -1
  },
  {
    "appid": 1050150,
    "peak_count": -1
  },
  {
    "appid": 1050160,
    "peak_count": -1
  },
  {
    "appid": 1050170,
    "peak_count": 0
  },
  {
    "appid": 1050180,
    "peak_count": -1
  },
  {
    "appid": 1050190,
    "peak_count": 2
  },
  {
    "appid": 1050210,
    "peak_count": -1
  },
  {
    "appid": 1050230,
    "peak_count": 2
  },
  {
    "appid": 1050280,
    "peak_count": 63
  },
  {
    "appid": 1050330,
    "peak_count": -1
  },
  {
    "appid": 1050340,
    "peak_count": -1
  },
  {
    "appid": 1050350,
    "peak_count": 2
  },
  {
    "appid": 1050430,
    "peak_count": -1
  },
  {
    "appid": 1050500,
    "peak_count": -1
  },
  {
    "appid": 1050520,
    "peak_count": -1
  },
  {
    "appid": 1050540,
    "peak_count": 1
  },
  {
    "appid": 1050560,
    "peak_count": 13
  },
  {
    "appid": 1050580,
    "peak_count": -1
  },
  {
    "appid": 1050620,
    "peak_count": -1
  },
  {
    "appid": 1050660,
    "peak_count": -1
  },
  {
    "appid": 1050670,
    "peak_count": -1
  },
  {
    "appid": 1050690,
    "peak_count": -1
  },
  {
    "appid": 1050720,
    "peak_count": -1
  },
  {
    "appid": 1050730,
    "peak_count": -1
  },
  {
    "appid": 1050810,
    "peak_count": -1
  },
  {
    "appid": 1050880,
    "peak_count": -1
  },
  {
    "appid": 1050900,
    "peak_count": -1
  },
  {
    "appid": 1050910,
    "peak_count": -1
  },
  {
    "appid": 105100,
    "peak_count": -1
  },
  {
    "appid": 1051060,
    "peak_count": -1
  },
  {
    "appid": 1051130,
    "peak_count": -1
  },
  {
    "appid": 1051160,
    "peak_count": 2
  },
  {
    "appid": 1051170,
    "peak_count": 2
  },
  {
    "appid": 1051200,
    "peak_count": 951
  },
  {
    "appid": 1051220,
    "peak_count": -1
  },
  {
    "appid": 1051250,
    "peak_count": 4
  },
  {
    "appid": 1051260,
    "peak_count": -1
  },
  {
    "appid": 1051270,
    "peak_count": -1
  },
  {
    "appid": 1051280,
    "peak_count": -1
  },
  {
    "appid": 1051290,
    "peak_count": -1
  },
  {
    "appid": 1051300,
    "peak_count": -1
  },
  {
    "appid": 1051310,
    "peak_count": 635
  },
  {
    "appid": 1051320,
    "peak_count": -1
  },
  {
    "appid": 1051330,
    "peak_count": -1
  },
  {
    "appid": 1051350,
    "peak_count": -1
  },
  {
    "appid": 1051470,
    "peak_count": -1
  },
  {
    "appid": 1051500,
    "peak_count": -1
  },
  {
    "appid": 1051570,
    "peak_count": -1
  },
  {
    "appid": 1051580,
    "peak_count": -1
  },
  {
    "appid": 1051600,
    "peak_count": -1
  },
  {
    "appid": 1051630,
    "peak_count": -1
  },
  {
    "appid": 1051690,
    "peak_count": 1134
  },
  {
    "appid": 1051830,
    "peak_count": -1
  },
  {
    "appid": 1051840,
    "peak_count": -1
  },
  {
    "appid": 1051850,
    "peak_count": -1
  },
  {
    "appid": 1051870,
    "peak_count": -1
  },
  {
    "appid": 1051890,
    "peak_count": -1
  },
  {
    "appid": 1051900,
    "peak_count": 4
  },
  {
    "appid": 1051920,
    "peak_count": 4
  },
  {
    "appid": 1051940,
    "peak_count": -1
  },
  {
    "appid": 1051960,
    "peak_count": 21
  },
  {
    "appid": 1051990,
    "peak_count": -1
  },
  {
    "appid": 1052010,
    "peak_count": -1
  },
  {
    "appid": 1052030,
    "peak_count": -1
  },
  {
    "appid": 1052070,
    "peak_count": -1
  },
  {
    "appid": 1052080,
    "peak_count": -1
  },
  {
    "appid": 1052100,
    "peak_count": -1
  },
  {
    "appid": 1052140,
    "peak_count": -1
  },
  {
    "appid": 1052150,
    "peak_count": -1
  },
  {
    "appid": 1052220,
    "peak_count": -1
  },
  {
    "appid": 1052250,
    "peak_count": -1
  },
  {
    "appid": 1052310,
    "peak_count": -1
  },
  {
    "appid": 1052330,
    "peak_count": -1
  },
  {
    "appid": 1052360,
    "peak_count": -1
  },
  {
    "appid": 1052370,
    "peak_count": -1
  },
  {
    "appid": 1052380,
    "peak_count": -1
  },
  {
    "appid": 1052420,
    "peak_count": -1
  },
  {
    "appid": 1052440,
    "peak_count": 46
  },
  {
    "appid": 1052470,
    "peak_count": -1
  },
  {
    "appid": 1052480,
    "peak_count": -1
  },
  {
    "appid": 1052500,
    "peak_count": -1
  },
  {
    "appid": 1052540,
    "peak_count": -1
  },
  {
    "appid": 1052550,
    "peak_count": 3
  },
  {
    "appid": 1052560,
    "peak_count": 1
  },
  {
    "appid": 1052580,
    "peak_count": 4
  },
  {
    "appid": 1052590,
    "peak_count": -1
  },
  {
    "appid": 1052600,
    "peak_count": 2
  },
  {
    "appid": 1052670,
    "peak_count": 1
  },
  {
    "appid": 1052760,
    "peak_count": -1
  },
  {
    "appid": 1052850,
    "peak_count": -1
  },
  {
    "appid": 1052870,
    "peak_count": 4
  },
  {
    "appid": 1052900,
    "peak_count": -1
  },
  {
    "appid": 1052920,
    "peak_count": -1
  },
  {
    "appid": 1052970,
    "peak_count": 12
  },
  {
    "appid": 1052990,
    "peak_count": 250
  },
  {
    "appid": 105300,
    "peak_count": 24
  },
  {
    "appid": 1053000,
    "peak_count": -1
  },
  {
    "appid": 1053020,
    "peak_count": -1
  },
  {
    "appid": 1053040,
    "peak_count": 1
  },
  {
    "appid": 1053060,
    "peak_count": 86
  },
  {
    "appid": 1053090,
    "peak_count": 2
  },
  {
    "appid": 1053160,
    "peak_count": 13
  },
  {
    "appid": 1053170,
    "peak_count": 171
  },
  {
    "appid": 1053190,
    "peak_count": -1
  },
  {
    "appid": 1053250,
    "peak_count": -1
  },
  {
    "appid": 1053300,
    "peak_count": -1
  },
  {
    "appid": 1053330,
    "peak_count": -1
  },
  {
    "appid": 1053560,
    "peak_count": -1
  },
  {
    "appid": 1053620,
    "peak_count": -1
  },
  {
    "appid": 1053640,
    "peak_count": -1
  },
  {
    "appid": 1053650,
    "peak_count": -1
  },
  {
    "appid": 1053660,
    "peak_count": -1
  },
  {
    "appid": 1053680,
    "peak_count": 167
  },
  {
    "appid": 1053700,
    "peak_count": -1
  },
  {
    "appid": 1053710,
    "peak_count": 26
  },
  {
    "appid": 1053720,
    "peak_count": -1
  },
  {
    "appid": 1053730,
    "peak_count": -1
  },
  {
    "appid": 1053740,
    "peak_count": -1
  },
  {
    "appid": 1053750,
    "peak_count": -1
  },
  {
    "appid": 1053760,
    "peak_count": 13
  },
  {
    "appid": 1053780,
    "peak_count": -1
  },
  {
    "appid": 1053820,
    "peak_count": -1
  },
  {
    "appid": 1053830,
    "peak_count": -1
  },
  {
    "appid": 1053850,
    "peak_count": -1
  },
  {
    "appid": 1053870,
    "peak_count": -1
  },
  {
    "appid": 1053920,
    "peak_count": 4
  },
  {
    "appid": 1053940,
    "peak_count": -1
  },
  {
    "appid": 1053960,
    "peak_count": -1
  },
  {
    "appid": 1054030,
    "peak_count": -1
  },
  {
    "appid": 1054040,
    "peak_count": -1
  },
  {
    "appid": 1054050,
    "peak_count": -1
  },
  {
    "appid": 1054090,
    "peak_count": -1
  },
  {
    "appid": 1054110,
    "peak_count": -1
  },
  {
    "appid": 1054150,
    "peak_count": -1
  },
  {
    "appid": 1054180,
    "peak_count": 1
  },
  {
    "appid": 1054240,
    "peak_count": -1
  },
  {
    "appid": 1054250,
    "peak_count": -1
  },
  {
    "appid": 1054270,
    "peak_count": -1
  },
  {
    "appid": 1054290,
    "peak_count": -1
  },
  {
    "appid": 1054300,
    "peak_count": -1
  },
  {
    "appid": 1054310,
    "peak_count": -1
  },
  {
    "appid": 1054340,
    "peak_count": 131
  },
  {
    "appid": 1054350,
    "peak_count": -1
  },
  {
    "appid": 1054430,
    "peak_count": 320
  },
  {
    "appid": 1054450,
    "peak_count": 14
  },
  {
    "appid": 1054490,
    "peak_count": 1392
  },
  {
    "appid": 105450,
    "peak_count": 9414
  },
  {
    "appid": 1054500,
    "peak_count": -1
  },
  {
    "appid": 1054510,
    "peak_count": 718
  },
  {
    "appid": 1054520,
    "peak_count": -1
  },
  {
    "appid": 1054550,
    "peak_count": -1
  },
  {
    "appid": 1054560,
    "peak_count": -1
  },
  {
    "appid": 1054570,
    "peak_count": 2
  },
  {
    "appid": 1054580,
    "peak_count": 21
  },
  {
    "appid": 1054590,
    "peak_count": -1
  },
  {
    "appid": 1054610,
    "peak_count": -1
  },
  {
    "appid": 1054620,
    "peak_count": 2
  },
  {
    "appid": 1054640,
    "peak_count": -1
  },
  {
    "appid": 1054650,
    "peak_count": -1
  },
  {
    "appid": 1054660,
    "peak_count": -1
  },
  {
    "appid": 1054690,
    "peak_count": 35
  },
  {
    "appid": 1054700,
    "peak_count": -1
  },
  {
    "appid": 1054710,
    "peak_count": 32
  },
  {
    "appid": 1054720,
    "peak_count": -1
  },
  {
    "appid": 1054750,
    "peak_count": 7
  },
  {
    "appid": 1054770,
    "peak_count": -1
  },
  {
    "appid": 1054790,
    "peak_count": -1
  },
  {
    "appid": 1054800,
    "peak_count": 1494
  },
  {
    "appid": 1054850,
    "peak_count": -1
  },
  {
    "appid": 1054900,
    "peak_count": -1
  },
  {
    "appid": 1054930,
    "peak_count": -1
  },
  {
    "appid": 1054980,
    "peak_count": -1
  },
  {
    "appid": 1054990,
    "peak_count": -1
  },
  {
    "appid": 1055000,
    "peak_count": -1
  },
  {
    "appid": 1055010,
    "peak_count": 201
  },
  {
    "appid": 1055020,
    "peak_count": 3
  },
  {
    "appid": 1055030,
    "peak_count": -1
  },
  {
    "appid": 1055090,
    "peak_count": 237
  },
  {
    "appid": 1055120,
    "peak_count": -1
  },
  {
    "appid": 1055140,
    "peak_count": -1
  },
  {
    "appid": 1055150,
    "peak_count": -1
  },
  {
    "appid": 1055170,
    "peak_count": -1
  },
  {
    "appid": 1055180,
    "peak_count": 1
  },
  {
    "appid": 1055210,
    "peak_count": 78
  },
  {
    "appid": 1055240,
    "peak_count": -1
  },
  {
    "appid": 1055280,
    "peak_count": 1
  },
  {
    "appid": 1055310,
    "peak_count": -1
  },
  {
    "appid": 1055360,
    "peak_count": -1
  },
  {
    "appid": 1055380,
    "peak_count": -1
  },
  {
    "appid": 1055420,
    "peak_count": -1
  },
  {
    "appid": 1055430,
    "peak_count": 177
  },
  {
    "appid": 1055460,
    "peak_count": -1
  },
  {
    "appid": 1055490,
    "peak_count": 21
  },
  {
    "appid": 1055540,
    "peak_count": 217
  },
  {
    "appid": 1055610,
    "peak_count": 34
  },
  {
    "appid": 1055620,
    "peak_count": 8
  },
  {
    "appid": 1055660,
    "peak_count": -1
  },
  {
    "appid": 1055690,
    "peak_count": -1
  },
  {
    "appid": 1055760,
    "peak_count": 88
  },
  {
    "appid": 1055770,
    "peak_count": -1
  },
  {
    "appid": 1055780,
    "peak_count": -1
  },
  {
    "appid": 1055870,
    "peak_count": -1
  },
  {
    "appid": 1055890,
    "peak_count": -1
  },
  {
    "appid": 1055930,
    "peak_count": -1
  },
  {
    "appid": 1055940,
    "peak_count": -1
  },
  {
    "appid": 1055950,
    "peak_count": 1
  },
  {
    "appid": 1055960,
    "peak_count": -1
  },
  {
    "appid": 1055970,
    "peak_count": -1
  },
  {
    "appid": 1055990,
    "peak_count": -1
  },
  {
    "appid": 105600,
    "peak_count": 486918
  },
  {
    "appid": 1056010,
    "peak_count": -1
  },
  {
    "appid": 1056070,
    "peak_count": -1
  },
  {
    "appid": 1056080,
    "peak_count": 5
  },
  {
    "appid": 1056140,
    "peak_count": -1
  },
  {
    "appid": 1056170,
    "peak_count": -1
  },
  {
    "appid": 1056180,
    "peak_count": 34
  },
  {
    "appid": 1056230,
    "peak_count": 9
  },
  {
    "appid": 1056280,
    "peak_count": -1
  },
  {
    "appid": 1056290,
    "peak_count": -1
  },
  {
    "appid": 1056320,
    "peak_count": -1
  },
  {
    "appid": 1056330,
    "peak_count": -1
  },
  {
    "appid": 1056350,
    "peak_count": 10
  },
  {
    "appid": 1056390,
    "peak_count": -1
  },
  {
    "appid": 1056420,
    "peak_count": -1
  },
  {
    "appid": 1056480,
    "peak_count": -1
  },
  {
    "appid": 1056490,
    "peak_count": 78
  },
  {
    "appid": 1056510,
    "peak_count": 12
  },
  {
    "appid": 1056570,
    "peak_count": 110
  },
  {
    "appid": 1056580,
    "peak_count": 14
  },
  {
    "appid": 1056590,
    "peak_count": -1
  },
  {
    "appid": 1056600,
    "peak_count": 5443
  },
  {
    "appid": 1056610,
    "peak_count": -1
  },
  {
    "appid": 1056640,
    "peak_count": 59197
  }
]