[
  {
    "appid": 1203500,
    "peak_count": 1
  },
  {
    "appid": 1203560,
    "peak_count": -1
  },
  {
    "appid": 1203570,
    "peak_count": -1
  },
  {
    "appid": 1203580,
    "peak_count": -1
  },
  {
    "appid": 1203600,
    "peak_count": 3
  },
  {
    "appid": 1203630,
    "peak_count": 833
  },
  {
    "appid": 1203650,
    "peak_count": -1
  },
  {
    "appid": 1203660,
    "peak_count": -1
  },
  {
    "appid": 1203680,
    "peak_count": -1
  },
  {
    "appid": 1203710,
    "peak_count": 432
  },
  {
    "appid": 1203740,
    "peak_count": -1
  },
  {
    "appid": 1203750,
    "peak_count": 7
  },
  {
    "appid": 1203760,
    "peak_count": -1
  },
  {
    "appid": 1203770,
    "peak_count": -1
  },
  {
    "appid": 1203780,
    "peak_count": -1
  },
  {
    "appid": 1203810,
    "peak_count": 1
  },
  {
    "appid": 1203850,
    "peak_count": -1
  },
  {
    "appid": 1203890,
    "peak_count": 14
  },
  {
    "appid": 1203910,
    "peak_count": -1
  },
  {
    "appid": 1203930,
    "peak_count": 154
  },
  {
    "appid": 1203950,
    "peak_count": -1
  },
  {
    "appid": 1203960,
    "peak_count": -1
  },
  {
    "appid": 1203970,
    "peak_count": -1
  },
  {
    "appid": 1203990,
    "peak_count": 7
  },
  {
    "appid": 1204030,
    "peak_count": -1
  },
  {
    "appid": 1204050,
    "peak_count": 168
  },
  {
    "appid": 1204080,
    "peak_count": -1
  },
  {
    "appid": 1204210,
    "peak_count": 1
  },
  {
    "appid": 1204220,
    "peak_count": -1
  },
  {
    "appid": 1204230,
    "peak_count": -1
  },
  {
    "appid": 1204250,
    "peak_count": -1
  },
  {
    "appid": 1204270,
    "peak_count": -1
  },
  {
    "appid": 1204280,
    "peak_count": -1
  },
  {
    "appid": 1204320,
    "peak_count": -1
  },
  {
    "appid": 1204330,
    "peak_count": -1
  },
  {
    "appid": 1204360,
    "peak_count": -1
  },
  {
    "appid": 1204370,
    "peak_count": -1
  },
  {
    "appid": 1204380,
    "peak_count": -1
  },
  {
    "appid": 1204410,
    "peak_count": -1
  },
  {
    "appid": 1204440,
    "peak_count": 5
  },
  {
    "appid": 1204470,
    "peak_count": -1
  },
  {
    "appid": 1204480,
    "peak_count": -1
  },
  {
    "appid": 1204490,
    "peak_count": 10
  },
  {
    "appid": 1204530,
    "peak_count": -1
  },
  {
    "appid": 1204540,
    "peak_count": -1
  },
  {
    "appid": 1204630,
    "peak_count": -1
  },
  {
    "appid": 1204650,
    "peak_count": 1
  },
  {
    "appid": 1204660,
    "peak_count": -1
  },
  {
    "appid": 1204670,
    "peak_count": -1
  },
  {
    "appid": 1204700,
    "peak_count": 21
  },
  {
    "appid": 1204710,
    "peak_count": -1
  },
  {
    "appid": 1204720,
    "peak_count": 24
  },
  {
    "appid": 1204760,
    "peak_count": -1
  },
  {
    "appid": 1204800,
    "peak_count": -1
  },
  {
    "appid": 1204860,
    "peak_count": -1
  },
  {
    "appid": 1204880,
    "peak_count": -1
  },
  {
    "appid": 1204930,
    "peak_count": 3
  },
  {
    "appid": 1204940,
    "peak_count": -1
  },
  {
    "appid": 1204950,
    "peak_count": -1
  },
  {
    "appid": 1204970,
    "peak_count": -1
  },
  {
    "appid": 1204990,
    "peak_count": 110
  },
  {
    "appid": 1205010,
    "peak_count": -1
  },
  {
    "appid": 1205020,
    "peak_count": 0
  },
  {
    "appid": 1205060,
    "peak_count": -1
  },
  {
    "appid": 1205140,
    "peak_count": -1
  },
  {
    "appid": 1205150,
    "peak_count": -1
  },
  {
    "appid": 1205160,
    "peak_count": 1
  },
  {
    "appid": 1205170,
    "peak_count": 37
  },
  {
    "appid": 1205240,
    "peak_count": 57
  },
  {
    "appid": 1205250,
    "peak_count": -1
  },
  {
    "appid": 1205260,
    "peak_count": -1
  },
  {
    "appid": 1205450,
    "peak_count": 339
  },
  {
    "appid": 1205480,
    "peak_count": 102
  },
  {
    "appid": 1205540,
    "peak_count": -1
  },
  {
    "appid": 1205590,
    "peak_count": -1
  },
  {
    "appid": 1205620,
    "peak_count": -1
  },
  {
    "appid": 1205650,
    "peak_count": -1
  },
  {
    "appid": 1205690,
    "peak_count": -1
  },
  {
    "appid": 1205800,
    "peak_count": -1
  },
  {
    "appid": 1205900,
    "peak_count": -1
  },
  {
    "appid": 1205960,
    "peak_count": 281
  },
  {
    "appid": 1205970,
    "peak_count": 335
  },
  {
    "appid": 1206000,
    "peak_count": -1
  },
  {
    "appid": 1206010,
    "peak_count": -1
  },
  {
    "appid": 1206040,
    "peak_count": 1
  },
  {
    "appid": 1206050,
    "peak_count": -1
  },
  {
    "appid": 1206060,
    "peak_count": 343
  },
  {
    "appid": 1206080,
    "peak_count": -1
  },
  {
    "appid": 1206090,
    "peak_count": -1
  },
  {
    "appid": 1206110,
    "peak_count": -1
  },
  {
    "appid": 1206140,
    "peak_count": -1
  },
  {
    "appid": 1206180,
    "peak_count": -1
  },
  {
    "appid": 1206230,
    "peak_count": -1
  },
  {
    "appid": 1206240,
    "peak_count": 57
  },
  {
    "appid": 1206260,
    "peak_count": 1
  },
  {
    "appid": 1206270,
    "peak_count": -1
  },
  {
    "appid": 1206280,
    "peak_count": -1
  },
  {
    "appid": 1206290,
    "peak_count": -1
  },
  {
    "appid": 1206310,
    "peak_count": -1
  },
  {
    "appid": 1206320,
    "peak_count": -1
  },
  {
    "appid": 1206350,
    "peak_count": -1
  },
  {
    "appid": 1206380,
    "peak_count": -1
  },
  {
    "appid": 1206430,
    "peak_count": 121
  },
  {
    "appid": 1206470,
    "peak_count": -1
  },
  {
    "appid": 1206480,
    "peak_count": 20
  },
  {
    "appid": 1206490,
    "peak_count": -1
  },
  {
    "appid": 1206510,
    "peak_count": 0
  },
  {
    "appid": 1206550,
    "peak_count": 1
  },
  {
    "appid": 1206560,
    "peak_count": 5139
  },
  {
    "appid": 1206570,
    "peak_count": -1
  },
  {
    "appid": 1206600,
    "peak_count": 365
  },
  {
    "appid": 1206610,
    "peak_count": 3597
  },
  {
    "appid": 1206670,
    "peak_count": -1
  },
  {
    "appid": 1206720,
    "peak_count": -1
  },
  {
    "appid": 1206730,
    "peak_count": -1
  },
  {
    "appid": 1206740,
    "peak_count": 40
  },
  {
    "appid": 1206770,
    "peak_count": -1
  },
  {
    "appid": 1206790,
    "peak_count": 4
  },
  {
    "appid": 1206810,
    "peak_count": 0
  },
  {
    "appid": 1206840,
    "peak_count": 1
  },
  {
    "appid": 1206870,
    "peak_count": -1
  },
  {
    "appid": 1206900,
    "peak_count": 2
  },
  {
    "appid": 1206910,
    "peak_count": -1
  },
  {
    "appid": 1206920,
    "peak_count": -1
  },
  {
    "appid": 1206930,
    "peak_count": 21
  },
  {
    "appid": 1206960,
    "peak_count": 5
  },
  {
    "appid": 1207010,
    "peak_count": -1
  },
  {
    "appid": 1207020,
    "peak_count": -1
  },
  {
    "appid": 1207030,
    "peak_count": -1
  },
  {
    "appid": 1207050,
    "peak_count": 249
  },
  {
    "appid": 1207130,
    "peak_count": -1
  },
  {
    "appid": 1207210,
    "peak_count": -1
  },
  {
    "appid": 1207260,
    "peak_count": -1
  },
  {
    "appid": 1207310,
    "peak_count": 17
  },
  {
    "appid": 1207320,
    "peak_count": -1
  },
  {
    "appid": 1207380,
    "peak_count": -1
  },
  {
    "appid": 1207390,
    "peak_count": -1
  },
  {
    "appid": 1207400,
    "peak_count": -1
  },
  {
    "appid": 1207420,
    "peak_count": -1
  },
  {
    "appid": 1207480,
    "peak_count": 2
  },
  {
    "appid": 1207500,
    "peak_count": -1
  },
  {
    "appid": 1207520,
    "peak_count": -1
  },
  {
    "appid": 1207540,
    "peak_count": -1
  },
  {
    "appid": 1207590,
    "peak_count": 674
  },
  {
    "appid": 1207650,
    "peak_count": 935
  },
  {
    "appid": 1207710,
    "peak_count": -1
  },
  {
    "appid": 1207770,
    "peak_count": -1
  },
  {
    "appid": 1207800,
    "peak_count": -1
  },
  {
    "appid": 1207840,
    "peak_count": -1
  },
  {
    "appid": 1207850,
    "peak_count": 1331
  },
  {
    "appid": 1207860,
    "peak_count": 2
  },
  {
    "appid": 1207880,
    "peak_count": 13
  },
  {
    "appid": 1208030,
    "peak_count": 3
  },
  {
    "appid": 1208050,
    "peak_count": -1
  },
  {
    "appid": 1208080,
    "peak_count": 41
  },
  {
    "appid": 1208090,
    "peak_count": 1
  },
  {
    "appid": 1208220,
    "peak_count": -1
  },
  {
    "appid": 1208240,
    "peak_count": -1
  },
  {
    "appid": 1208260,
    "peak_count": 29
  },
  {
    "appid": 1208330,
    "peak_count": -1
  },
  {
    "appid": 1208370,
    "peak_count": 2
  },
  {
    "appid": 1208380,
    "peak_count": -1
  },
  {
    "appid": 1208390,
    "peak_count": -1
  },
  {
    "appid": 1208400,
    "peak_count": -1
  },
  {
    "appid": 1208420,
    "peak_count": -1
  },
  {
    "appid": 1208460,
    "peak_count": -1
  },
  {
    "appid": 1208510,
    "peak_count": -1
  },
  {
    "appid": 1208520,
    "peak_count": -1
  },
  {
    "appid": 1208540,
    "peak_count": -1
  },
  {
    "appid": 1208550,
    "peak_count": 5
  },
  {
    "appid": 1208580,
    "peak_count": -1
  },
  {
    "appid": 1208590,
    "peak_count": 14
  },
  {
    "appid": 1208600,
    "peak_count": -1
  },
  {
    "appid": 1208760,
    "peak_count": -1
  },
  {
    "appid": 1208770,
    "peak_count": -1
  },
  {
    "appid": 1208810,
    "peak_count": -1
  },
  {
    "appid": 1208840,
    "peak_count": 1
  },
  {
    "appid": 1208870,
    "peak_count": -1
  },
  {
    "appid": 1208900,
    "peak_count": -1
  },
  {
    "appid": 1208910,
    "peak_count": -1
  },
  {
    "appid": 1208950,
    "peak_count": -1
  },
  {
    "appid": 1208980,
    "peak_count": -1
  },
  {
    "appid": 1209000,
    "peak_count": -1
  },
  {
    "appid": 1209040,
    "peak_count": 1964
  },
  {
    "appid": 1209060,
    "peak_count": -1
  },
  {
    "appid": 1209080,
    "peak_count": -1
  },
  {
    "appid": 1209140,
    "peak_count": -1
  },
  {
    "appid": 1209160,
    "peak_count": -1
  },
  {
    "appid": 1209170,
    "peak_count": -1
  },
  {
    "appid": 1209190,
    "peak_count": -1
  },
  {
    "appid": 1209200,
    "peak_count": -1
  },
  {
    "appid": 1209360,
    "peak_count": 30
  },
  {
    "appid": 1209410,
    "peak_count": 593
  },
  {
    "appid": 1209430,
    "peak_count": -1
  },
  {
    "appid": 1209440,
    "peak_count": -1
  },
  {
    "appid": 1209450,
    "peak_count": -1
  },
  {
    "appid": 1209490,
    "peak_count": 674
  },
  {
    "appid": 1209520,
    "peak_count": -1
  },
  {
    "appid": 1209570,
    "peak_count": -1
  },
  {
    "appid": 1209610,
    "peak_count": -1
  },
  {
    "appid": 1209650,
    "peak_count": -1
  },
  {
    "appid": 1209720,
    "peak_count": -1
  },
  {
    "appid": 1209740,
    "peak_count": -1
  },
  {
    "appid": 1209750,
    "peak_count": -1
  },
  {
    "appid": 1209760,
    "peak_count": -1
  },
  {
    "appid": 1209770,
    "peak_count": 23
  },
  {
    "appid": 1209860,
    "peak_count": -1
  },
  {
    "appid": 1209910,
    "peak_count": -1
  },
  {
    "appid": 1209980,
    "peak_count": -1
  },
  {
    "appid": 1209990,
    "peak_count": -1
  },
  {
    "appid": 12100,
    "peak_count": 619
  },
  {
    "appid": 1210010,
    "peak_count": 6
  },
  {
    "appid": 1210030,
    "peak_count": 528
  },
  {
    "appid": 1210060,
    "peak_count": -1
  },
  {
    "appid": 1210150,
    "peak_count": -1
  },
  {
    "appid": 1210230,
    "peak_count": -1
  },
  {
    "appid": 1210250,
    "peak_count": 746
  },
  {
    "appid": 1210260,
    "peak_count": -1
  },
  {
    "appid": 1210320,
    "peak_count": 7010
  },
  {
    "appid": 1210330,
    "peak_count": -1
  },
  {
    "appid": 1210340,
    "peak_count": -1
  },
  {
    "appid": 1210380,
    "peak_count": -1
  },
  {
    "appid": 1210410,
    "peak_count": -1
  },
  {
    "appid": 1210490,
    "peak_count": -1
  },
  {
    "appid": 1210550,
    "peak_count": -1
  },
  {
    "appid": 1210570,
    "peak_count": -1
  },
  {
    "appid": 1210590,
    "peak_count": -1
  },
  {
    "appid": 1210610,
    "peak_count": 7
  },
  {
    "appid": 1210620,
    "peak_count": -1
  },
  {
    "appid": 1210640,
    "peak_count": -1
  },
  {
    "appid": 1210650,
    "peak_count": 7
  },
  {
    "appid": 1210660,
    "peak_count": -1
  },
  {
    "appid": 1210670,
    "peak_count": -1
  },
  {
    "appid": 1210680,
    "peak_count": -1
  },
  {
    "appid": 1210700,
    "peak_count": -1
  },
  {
    "appid": 1210740,
    "peak_count": 21
  },
  {
    "appid": 1210770,
    "peak_count": -1
  },
  {
    "appid": 1210780,
    "peak_count": -1
  },
  {
    "appid": 1210790,
    "peak_count": 1
  },
  {
    "appid": 1210800,
    "peak_count": 8
  },
  {
    "appid": 1210830,
    "peak_count": -1
  },
  {
    "appid": 1210850,
    "peak_count": -1
  },
  {
    "appid": 1210880,
    "peak_count": -1
  },
  {
    "appid": 1210910,
    "peak_count": 2
  },
  {
    "appid": 1210930,
    "peak_count": -1
  },
  {
    "appid": 1210960,
    "peak_count": -1
  },
  {
    "appid": 1210970,
    "peak_count": -1
  },
  {
    "appid": 12110,
    "peak_count": 1212
  },
  {
    "appid": 1211020,
    "peak_count": 3121
  },
  {
    "appid": 1211050,
    "peak_count": -1
  },
  {
    "appid": 1211060,
    "peak_count": -1
  },
  {
    "appid": 1211070,
    "peak_count": -1
  },
  {
    "appid": 1211100,
    "peak_count": -1
  },
  {
    "appid": 1211110,
    "peak_count": 31
  },
  {
    "appid": 1211160,
    "peak_count": -1
  },
  {
    "appid": 1211180,
    "peak_count": -1
  },
  {
    "appid": 1211230,
    "peak_count": -1
  },
  {
    "appid": 1211240,
    "peak_count": 14
  },
  {
    "appid": 1211250,
    "peak_count": -1
  },
  {
    "appid": 1211320,
    "peak_count": -1
  },
  {
    "appid": 1211350,
    "peak_count": 1
  },
  {
    "appid": 1211360,
    "peak_count": -1
  },
  {
    "appid": 1211370,
    "peak_count": -1
  },
  {
    "appid": 1211420,
    "peak_count": -1
  },
  {
    "appid": 1211490,
    "peak_count": -1
  },
  {
    "appid": 1211540,
    "peak_count": -1
  },
  {
    "appid": 1211610,
    "peak_count": 1
  },
  {
    "appid": 1211630,
    "peak_count": 10435
  },
  {
    "appid": 1211640,
    "peak_count": -1
  },
  {
    "appid": 1211650,
    "peak_count": -1
  },
  {
    "appid": 1211700,
    "peak_count": -1
  },
  {
    "appid": 1211730,
    "peak_count": -1
  },
  {
    "appid": 1211740,
    "peak_count": -1
  },
  {
    "appid": 1211780,
    "peak_count": -1
  },
  {
    "appid": 1211790,
    "peak_count": -1
  },
  {
    "appid": 1211800,
    "peak_count": 1
  },
  {
    "appid": 1211830,
    "peak_count": -1
  },
  {
    "appid": 1211930,
    "peak_count": 22
  },
  {
    "appid": 1211950,
    "peak_count": -1
  },
  {
    "appid": 1211960,
    "peak_count": -1
  },
  {
    "appid": 1211990,
    "peak_count": 2
  },
  {
    "appid": 12120,
    "peak_count": 3387
  },
  {
    "appid": 1212040,
    "peak_count": -1
  },
  {
    "appid": 1212100,
    "peak_count": -1
  },
  {
    "appid": 1212110,
    "peak_count": -1
  },
  {
    "appid": 1212170,
    "peak_count": 5
  },
  {
    "appid": 1212190,
    "peak_count": -1
  },
  {
    "appid": 1212290,
    "peak_count": 4
  },
  {
    "appid": 1212300,
    "peak_count": 2
  },
  {
    "appid": 1212320,
    "peak_count": -1
  },
  {
    "appid": 1212330,
    "peak_count": -1
  },
  {
    "appid": 1212360,
    "peak_count": -1
  },
  {
    "appid": 1212370,
    "peak_count": -1
  },
  {
    "appid": 1212400,
    "peak_count": -1
  },
  {
    "appid": 1212410,
    "peak_count": 44
  },
  {
    "appid": 1212440,
    "peak_count": 1
  },
  {
    "appid": 1212450,
    "peak_count": -1
  },
  {
    "appid": 1212470,
    "peak_count": -1
  },
  {
    "appid": 1212480,
    "peak_count": -1
  },
  {
    "appid": 1212530,
    "peak_count": -1
  },
  {
    "appid": 1212610,
    "peak_count": -1
  },
  {
    "appid": 1212620,
    "peak_count": 245
  },
  {
    "appid": 1212640,
    "peak_count": -1
  },
  {
    "appid": 1212710,
    "peak_count": -1
  },
  {
    "appid": 1212720,
    "peak_count": -1
  },
  {
    "appid": 1212730,
    "peak_count": -1
  },
  {
    "appid": 1212740,
    "peak_count": 1
  },
  {
    "appid": 1212750,
    "peak_count": 0
  },
  {
    "appid": 1212830,
    "peak_count": -1
  },
  {
    "appid": 1212840,
    "peak_count": -1
  },
  {
    "appid": 1212850,
    "peak_count": -1
  },
  {
    "appid": 1212860,
    "peak_count": -1
  },
  {
    "appid": 1212930,
    "peak_count": -1
  },
  {
    "appid": 1212940,
    "peak_count": -1
  },
  {
    "appid": 1212960,
    "peak_count": -1
  },
  {
    "appid": 1213000,
    "peak_count": 13
  },
  {
    "appid": 1213050,
    "peak_count": -1
  },
  {
    "appid": 1213070,
    "peak_count": -1
  },
  {
    "appid": 1213140,
    "peak_count": -1
  },
  {
    "appid": 1213150,
    "peak_count": -1
  },
  {
    "appid": 1213180,
    "peak_count": -1
  },
  {
    "appid": 1213210,
    "peak_count": 29136
  },
  {
    "appid": 1213220,
    "peak_count": 15
  },
  {
    "appid": 1213230,
    "peak_count": 95
  },
  {
    "appid": 1213370,
    "peak_count": -1
  },
  {
    "appid": 1213390,
    "peak_count": 8
  },
  {
    "appid": 1213420,
    "peak_count": 8
  },
  {
    "appid": 1213450,
    "peak_count": -1
  },
  {
    "appid": 1213460,
    "peak_count": -1
  },
  {
    "appid": 1213570,
    "peak_count": 11
  },
  {
    "appid": 1213600,
    "peak_count": -1
  },
  {
    "appid": 1213640,
    "peak_count": -1
  },
  {
    "appid": 1213650,
    "peak_count": -1
  },
  {
    "appid": 1213660,
    "peak_count": -1
  },
  {
    "appid": 1213670,
    "peak_count": 72
  },
  {
    "appid": 1213680,
    "peak_count": 3
  },
  {
    "appid": 1213700,
    "peak_count": 431
  },
  {
    "appid": 1213710,
    "peak_count": -1
  },
  {
    "appid": 1213740,
    "peak_count": 15594
  },
  {
    "appid": 1213750,
    "peak_count": 257
  },
  {
    "appid": 1213760,
    "peak_count": -1
  },
  {
    "appid": 1213770,
    "peak_count": -1
  },
  {
    "appid": 1213780,
    "peak_count": -1
  },
  {
    "appid": 1213810,
    "peak_count": 0
  },
  {
    "appid": 1213860,
    "peak_count": -1
  },
  {
    "appid": 1213870,
    "peak_count": -1
  },
  {
    "appid": 1213890,
    "peak_count": -1
  },
  {
    "appid": 1213910,
    "peak_count": -1
  },
  {
    "appid": 1213980,
    "peak_count": -1
  },
  {
    "appid": 12140,
    "peak_count": 410
  },
  {
    "appid": 1214050,
    "peak_count": -1
  },
  {
    "appid": 1214060,
    "peak_count": -1
  },
  {
    "appid": 1214130,
    "peak_count": 1
  },
  {
    "appid": 1214150,
    "peak_count": -1
  },
  {
    "appid": 1214180,
    "peak_count": -1
  },
  {
    "appid": 1214200,
    "peak_count": -1
  },
  {
    "appid": 1214210,
    "peak_count": -1
  },
  {
    "appid": 1214250,
    "peak_count": -1
  },
  {
    "appid": 1214280,
    "peak_count": 430
  },
  {
    "appid": 1214320,
    "peak_count": -1
  },
  {
    "appid": 1214360,
    "peak_count": 138
  },
  {
    "appid": 1214380,
    "peak_count": 0
  },
  {
    "appid": 1214400,
    "peak_count": 1
  },
  {
    "appid": 1214410,
    "peak_count": -1
  },
  {
    "appid": 1214450,
    "peak_count": 12
  },
  {
    "appid": 1214460,
    "peak_count": -1
  },
  {
    "appid": 1214500,
    "peak_count": -1
  },
  {
    "appid": 1214520,
    "peak_count": -1
  },
  {
    "appid": 1214530,
    "peak_count": 1
  },
  {
    "appid": 1214540,
    "peak_count": 36
  },
  {
    "appid": 1214570,
    "peak_count": -1
  },
  {
    "appid": 1214590,
    "peak_count": 2
  },
  {
    "appid": 1214600,
    "peak_count": -1
  },
  {
    "appid": 1214630,
    "peak_count": -1
  },
  {
    "appid": 1214680,
    "peak_count": -1
  },
  {
    "appid": 1214760,
    "peak_count": -1
  },
  {
    "appid": 1214850,
    "peak_count": -1
  },
  {
    "appid": 1214920,
    "peak_count": -1
  },
  {
    "appid": 1214980,
    "peak_count": -1
  },
  {
    "appid": 1214990,
    "peak_count": 0
  },
  {
    "appid": 12150,
    "peak_count": 179
  },
  {
    "appid": 1215000,
    "peak_count": -1
  },
  {
    "appid": 1215060,
    "peak_count": -1
  },
  {
    "appid": 1215120,
    "peak_count": -1
  },
  {
    "appid": 1215180,
    "peak_count": 406
  },
  {
    "appid": 1215200,
    "peak_count": -1
  },
  {
    "appid": 1215260,
    "peak_count": 152
  },
  {
    "appid": 1215270,
    "peak_count": 21
  },
  {
    "appid": 1215280,
    "peak_count": -1
  },
  {
    "appid": 1215310,
    "peak_count": 1
  },
  {
    "appid": 1215320,
    "peak_count": -1
  },
  {
    "appid": 1215340,
    "peak_count": -1
  },
  {
    "appid": 1215350,
    "peak_count": -1
  },
  {
    "appid": 1215380,
    "peak_count": -1
  },
  {
    "appid": 1215390,
    "peak_count": 1034
  },
  {
    "appid": 1215410,
    "peak_count": -1
  },
  {
    "appid": 1215430,
    "peak_count": -1
  },
  {
    "appid": 1215500,
    "peak_count": -1
  },
  {
    "appid": 1215520,
    "peak_count": -1
  },
  {
    "appid": 1215540,
    "peak_count": 1
  },
  {
    "appid": 1215550,
    "peak_count": -1
  },
  {
    "appid": 1215600,
    "peak_count": -1
  },
  {
    "appid": 1215650,
    "peak_count": -1
  },
  {
    "appid": 1215660,
    "peak_count": -1
  },
  {
    "appid": 1215690,
    "peak_count": -1
  },
  {
    "appid": 1215700,
    "peak_count": 1
  },
  {
    "appid": 1215710,
    "peak_count": -1
  },
  {
    "appid": 1215740,
    "peak_count": -1
  },
  {
    "appid": 1215750,
    "peak_count": -1
  },
  {
    "appid": 1215830,
    "peak_count": -1
  },
  {
    "appid": 1215860,
    "peak_count": 5
  },
  {
    "appid": 1215870,
    "peak_count": -1
  },
  {
    "appid": 1215900,
    "peak_count": -1
  },
  {
    "appid": 1215930,
    "peak_count": -1
  },
  {
    "appid": 1215950,
    "peak_count": -1
  },
  {
    "appid": 1215960,
    "peak_count": -1
  },
  {
    "appid": 1215980,
    "peak_count": -1
  },
  {
    "appid": 12160,
    "peak_count": -1
  },
  {
    "appid": 1216030,
    "peak_count": -1
  },
  {
    "appid": 1216050,
    "peak_count": -1
  },
  {
    "appid": 1216060,
    "peak_count": 12324
  },
  {
    "appid": 1216080,
    "peak_count": 17
  },
  {
    "appid": 1216150,
    "peak_count": 1
  },
  {
    "appid": 1216200,
    "peak_count": 493
  },
  {
    "appid": 1216220,
    "peak_count": 13
  },
  {
    "appid": 1216230,
    "peak_count": 21
  },
  {
    "appid": 1216300,
    "peak_count": -1
  },
  {
    "appid": 1216310,
    "peak_count": -1
  },
  {
    "appid": 1216320,
    "peak_count": 890
  },
  {
    "appid": 1216350,
    "peak_count": 8
  },
  {
    "appid": 1216470,
    "peak_count": 100
  },
  {
    "appid": 1216480,
    "peak_count": 0
  },
  {
    "appid": 1216490,
    "peak_count": -1
  },
  {
    "appid": 1216540,
    "peak_count": 3
  },
  {
    "appid": 1216550,
    "peak_count": 15
  },
  {
    "appid": 1216590,
    "peak_count": -1
  },
  {
    "appid": 1216600,
    "peak_count": -1
  },
  {
    "appid": 1216700,
    "peak_count": 1
  },
  {
    "appid": 1216710,
    "peak_count": 1959
  },
  {
    "appid": 1216720,
    "peak_count": -1
  },
  {
    "appid": 1216740,
    "peak_count": -1
  },
  {
    "appid": 1216880,
    "peak_count": 141
  },
  {
    "appid": 1216930,
    "peak_count": -1
  },
  {
    "appid": 1216980,
    "peak_count": 18
  },
  {
    "appid": 12170,
    "peak_count": 123
  },
  {
    "appid": 1217050,
    "peak_count": 12
  },
  {
    "appid": 1217060,
    "peak_count": 35002
  },
  {
    "appid": 1217070,
    "peak_count": -1
  },
  {
    "appid": 1217160,
    "peak_count": -1
  },
  {
    "appid": 1217190,
    "peak_count": -1
  },
  {
    "appid": 1217200,
    "peak_count": -1
  },
  {
    "appid": 1217220,
    "peak_count": -1
  },
  {
    "appid": 1217250,
    "peak_count": -1
  },
  {
    "appid": 1217260,
    "peak_count": -1
  },
  {
    "appid": 1217280,
    "peak_count": -1
  },
  {
    "appid": 1217310,
    "peak_count": -1
  },
  {
    "appid": 1217330,
    "peak_count": -1
  },
  {
    "appid": 1217340,
    "peak_count": -1
  },
  {
    "appid": 1217370,
    "peak_count": -1
  },
  {
    "appid": 1217380,
    "peak_count": 21
  },
  {
    "appid": 1217390,
    "peak_count": 763
  },
  {
    "appid": 1217440,
    "peak_count": -1
  },
  {
    "appid": 1217480,
    "peak_count": -1
  },
  {
    "appid": 1217490,
    "peak_count": -1
  },
  {
    "appid": 1217510,
    "peak_count": -1
  },
  {
    "appid": 1217520,
    "peak_count": -1
  },
  {
    "appid": 1217550,
    "peak_count": -1
  },
  {
    "appid": 1217560,
    "peak_count": -1
  },
  {
    "appid": 1217570,
    "peak_count": 14
  },
  {
    "appid": 1217580,
    "peak_count": -1
  },
  {
    "appid": 1217610,
    "peak_count": -1
  },
  {
    "appid": 1217630,
    "peak_count": -1
  },
  {
    "appid": 1217660,
    "peak_count": -1
  },
  {
    "appid": 1217720,
    "peak_count": -1
  },
  {
    "appid": 1217750,
    "peak_count": -1
  },
  {
    "appid": 1217820,
    "peak_count": -1
  },
  {
    "appid": 1217830,
    "peak_count": 19
  },
  {
    "appid": 1217860,
    "peak_count": -1
  },
  {
    "appid": 1217870,
    "peak_count": -1
  },
  {
    "appid": 1217880,
    "peak_count": 1
  },
  {
    "appid": 1217930,
    "peak_count": 11
  },
  {
    "appid": 12180,
    "peak_count": -1
  },
  {
    "appid": 1218010,
    "peak_count": 83
  },
  {
    "appid": 1218030,
    "peak_count": -1
  },
  {
    "appid": 1218090,
    "peak_count": 0
  },
  {
    "appid": 1218110,
    "peak_count": 1
  },
  {
    "appid": 1218140,
    "peak_count": -1
  },
  {
    "appid": 1218170,
    "peak_count": 158
  },
  {
    "appid": 1218200,
    "peak_count": -1
  },
  {
    "appid": 1218210,
    "peak_count": 3987
  },
  {
    "appid": 1218230,
    "peak_count": -1
  },
  {
    "appid": 1218250,
    "peak_count": 252
  },
  {
    "appid": 1218260,
    "peak_count": -1
  },
  {
    "appid": 1218280,
    "peak_count": 73
  },
  {
    "appid": 1218310,
    "peak_count": -1
  },
  {
    "appid": 1218320,
    "peak_count": -1
  },
  {
    "appid": 1218360,
    "peak_count": 75
  },
  {
    "appid": 1218420,
    "peak_count": -1
  },
  {
    "appid": 1218440,
    "peak_count": -1
  },
  {
    "appid": 1218480,
    "peak_count": -1
  },
  {
    "appid": 1218500,
    "peak_count": 1286
  },
  {
    "appid": 1218530,
    "peak_count": -1
  },
  {
    "appid": 1218550,
    "peak_count": -1
  },
  {
    "appid": 1218570,
    "peak_count": -1
  },
  {
    "appid": 1218580,
    "peak_count": -1
  },
  {
    "appid": 1218590,
    "peak_count": -1
  },
  {
    "appid": 1218640,
    "peak_count": -1
  },
  {
    "appid": 1218670,
    "peak_count": -1
  },
  {
    "appid": 1218680,
    "peak_count": -1
  },
  {
    "appid": 1218710,
    "peak_count": 1
  },
  {
    "appid": 1218740,
    "peak_count": 4340
  },
  {
    "appid": 1218750,
    "peak_count": -1
  },
  {
    "appid": 1218760,
    "peak_count": -1
  },
  {
    "appid": 1218770,
    "peak_count": -1
  },
  {
    "appid": 1218790,
    "peak_count": -1
  },
  {
    "appid": 1218810,
    "peak_count": 31
  },
  {
    "appid": 1218830,
    "peak_count": 2
  },
  {
    "appid": 1218850,
    "peak_count": -1
  },
  {
    "appid": 1218890,
    "peak_count": 92
  },
  {
    "appid": 1218900,
    "peak_count": 1272
  },
  {
    "appid": 1218920,
    "peak_count": 11
  },
  {
    "appid": 1218940,
    "peak_count": 4
  },
  {
    "appid": 1218950,
    "peak_count": -1
  },
  {
    "appid": 1219010,
    "peak_count": -1
  },
  {
    "appid": 1219020,
    "peak_count": 2
  },
  {
    "appid": 1219030,
    "peak_count": 3
  },
  {
    "appid": 1219060,
    "peak_count": -1
  },
  {
    "appid": 1219070,
    "peak_count": 3
  },
  {
    "appid": 1219080,
    "peak_count": -1
  },
  {
    "appid": 1219110,
    "peak_count": -1
  },
  {
    "appid": 1219120,
    "peak_count": -1
  },
  {
    "appid": 1219140,
    "peak_count": 0
  },
  {
    "appid": 1219170,
    "peak_count": -1
  },
  {
    "appid": 1219180,
    "peak_count": 0
  },
  {
    "appid": 1219220,
    "peak_count": -1
  },
  {
    "appid": 1219230,
    "peak_count": -1
  },
  {
    "appid": 1219300,
    "peak_count": 2
  },
  {
    "appid": 1219310,
    "peak_count": -1
  },
  {
    "appid": 1219320,
    "peak_count": -1
  },
  {
    "appid": 1219420,
    "peak_count": -1
  },
  {
    "appid": 1219450,
    "peak_count": -1
  },
  {
    "appid": 1219480,
    "peak_count": -1
  },
  {
    "appid": 1219500,
    "peak_count": -1
  },
  {
    "appid": 1219540,
    "peak_count": -1
  },
  {
    "appid": 1219580,
    "peak_count": 3
  },
  {
    "appid": 1219590,
    "peak_count": 540
  },
  {
    "appid": 1219600,
    "peak_count": -1
  },
  {
    "appid": 1219610,
    "peak_count": 4
  },
  {
    "appid": 1219650,
    "peak_count": -1
  },
  {
    "appid": 1219700,
    "peak_count": -1
  },
  {
    "appid": 1219730,
    "peak_count": 1
  },
  {
    "appid": 1219740,
    "peak_count": -1
  },
  {
    "appid": 1219790,
    "peak_count": 1
  },
  {
    "appid": 1219820,
    "peak_count": -1
  },
  {
    "appid": 1219860,
    "peak_count": -1
  },
  {
    "appid": 1219890,
    "peak_count": -1
  },
  {
    "appid": 1219910,
    "peak_count": -1
  },
  {
    "appid": 1219940,
    "peak_count": -1
  },
  {
    "appid": 1219950,
    "peak_count": 38
  },
  {
    "appid": 1219980,
    "peak_count": 3
  },
  {
    "appid": 12200,
    "peak_count": 1978
  },
  {
    "appid": 1220010,
    "peak_count": 20036
  },
  {
    "appid": 1220040,
    "peak_count": -1
  },
  {
    "appid": 1220070,
    "peak_count": 0
  },
  {
    "appid": 1220080,
    "peak_count": -1
  },
  {
    "appid": 1220120,
    "peak_count": -1
  },
  {
    "appid": 1220140,
    "peak_count": 2240
  },
  {
    "appid": 1220150,
    "peak_count": 286
  },
  {
    "appid": 1220160,
    "peak_count": 7
  },
  {
    "appid": 1220200,
    "peak_count": -1
  },
  {
    "appid": 1220330,
    "peak_count": 4
  },
  {
    "appid": 1220340,
    "peak_count": -1
  },
  {
    "appid": 1220370,
    "peak_count": -1
  },
  {
    "appid": 1220440,
    "peak_count": -1
  },
  {
    "appid": 1220460,
    "peak_count": -1
  },
  {
    "appid": 1220510,
    "peak_count": -1
  },
  {
    "appid": 1220520,
    "peak_count": -1
  },
  {
    "appid": 1220540,
    "peak_count": -1
  },
  {
    "appid": 1220580,
    "peak_count": -1
  },
  {
    "appid": 1220600,
    "peak_count": -1
  },
  {
    "appid": 1220680,
    "peak_count": -1
  },
  {
    "appid": 1220690,
    "peak_count": 1
  },
  {
    "appid": 1220710,
    "peak_count": -1
  },
  {
    "appid": 1220830,
    "peak_count": -1
  },
  {
    "appid": 1220840,
    "peak_count": 3357
  },
  {
    "appid": 1220850,
    "peak_count": -1
  },
  {
    "appid": 1220880,
    "peak_count": -1
  },
  {
    "appid": 1220890,
    "peak_count": 23
  },
  {
    "appid": 1220900,
    "peak_count": 14
  },
  {
    "appid": 1220910,
    "peak_count": -1
  },
  {
    "appid": 1220930,
    "peak_count": 49
  },
  {
    "appid": 1220990,
    "peak_count": -1
  },
  {
    "appid": 12210,
    "peak_count": 11696
  },
  {
    "appid": 1221050,
    "peak_count": 21
  },
  {
    "appid": 1221070,
    "peak_count": 1
  },
  {
    "appid": 1221080,
    "peak_count": 119
  },
  {
    "appid": 1221230,
    "peak_count": 4
  },
  {
    "appid": 1221240,
    "peak_count": 1
  },
  {
    "appid": 1221250,
    "peak_count": 111
  },
  {
    "appid": 1221280,
    "peak_count": -1
  },
  {
    "appid": 1221290,
    "peak_count": 18
  },
  {
    "appid": 1221320,
    "peak_count": -1
  },
  {
    "appid": 1221330,
    "peak_count": -1
  },
  {
    "appid": 1221390,
    "peak_count": -1
  },
  {
    "appid": 1221400,
    "peak_count": -1
  },
  {
    "appid": 1221420,
    "peak_count": -1
  },
  {
    "appid": 1221430,
    "peak_count": -1
  },
  {
    "appid": 1221440,
    "peak_count": -1
  },
  {
    "appid": 1221460,
    "peak_count": -1
  },
  {
    "appid": 1221510,
    "peak_count": -1
  },
  {
    "appid": 1221520,
    "peak_count": -1
  },
  {
    "appid": 1221540,
    "peak_count": 81
  },
  {
    "appid": 1221590,
    "peak_count": 9
  },
  {
    "appid": 1221600,
    "peak_count": -1
  },
  {
    "appid": 1221620,
    "peak_count": -1
  },
  {
    "appid": 1221630,
    "peak_count": -1
  },
  {
    "appid": 1221640,
    "peak_count": -1
  },
  {
    "appid": 1221650,
    "peak_count": -1
  },
  {
    "appid": 1221660,
    "peak_count": 0
  },
  {
    "appid": 1221730,
    "peak_count": -1
  },
  {
    "appid": 1221800,
    "peak_count": -1
  },
  {
    "appid": 1221830,
    "peak_count": -1
  },
  {
    "appid": 1221860,
    "peak_count": -1
  },
  {
    "appid": 1221880,
    "peak_count": -1
  },
  {
    "appid": 1221890,
    "peak_count": -1
  },
  {
    "appid": 1221980,
    "peak_count": -1
  },
  {
    "appid": 1221990,
    "peak_count": 6
  },
  {
    "appid": 12220,
    "peak_count": 2953
  },
  {
    "appid": 1222000,
    "peak_count": 1
  },
  {
    "appid": 1222020,
    "peak_count": -1
  },
  {
    "appid": 1222040,
    "peak_count": 13
  },
  {
    "appid": 1222050,
    "peak_count": -1
  },
  {
    "appid": 1222060,
    "peak_count": -1
  },
  {
    "appid": 1222080,
    "peak_count": -1
  },
  {
    "appid": 1222090,
    "peak_count": -1
  },
  {
    "appid": 1222120,
    "peak_count": -1
  },
  {
    "appid": 1222130,
    "peak_count": -1
  },
  {
    "appid": 1222140,
    "peak_count": 7194
  },
  {
    "appid": 1222160,
    "peak_count": -1
  },
  {
    "appid": 1222170,
    "peak_count": -1
  },
  {
    "appid": 1222180,
    "peak_count": -1
  },
  {
    "appid": 1222210,
    "peak_count": 85
  },
  {
    "appid": 1222220,
    "peak_count": -1
  },
  {
    "appid": 1222230,
    "peak_count": 2
  },
  {
    "appid": 1222240,
    "peak_count": -1
  },
  {
    "appid": 1222250,
    "peak_count": -1
  },
  {
    "appid": 1222260,
    "peak_count": -1
  },
  {
    "appid": 1222270,
    "peak_count": -1
  },
  {
    "appid": 1222300,
    "peak_count": 124
  },
  {
    "appid": 1222340,
    "peak_count": -1
  },
  {
    "appid": 1222360,
    "peak_count": 7
  },
  {
    "appid": 1222370,
    "peak_count": 5452
  },
  {
    "appid": 1222380,
    "peak_count": -1
  },
  {
    "appid": 1222390,
    "peak_count": -1
  },
  {
    "appid": 1222400,
    "peak_count": 66
  },
  {
    "appid": 1222480,
    "peak_count": -1
  },
  {
    "appid": 1222570,
    "peak_count": -1
  },
  {
    "appid": 1222600,
    "peak_count": 6
  },
  {
    "appid": 1222610,
    "peak_count": -1
  },
  {
    "appid": 1222670,
    "peak_count": 96185
  },
  {
    "appid": 1222680,
    "peak_count": 85230
  },
  {
    "appid": 1222690,
    "peak_count": 4092
  },
  {
    "appid": 1222700,
    "peak_count": 2124
  },
  {
    "appid": 1222720,
    "peak_count": -1
  },
  {
    "appid": 1222730,
    "peak_count": 35721
  },
  {
    "appid": 1222800,
    "peak_count": 1438
  },
  {
    "appid": 1222840,
    "peak_count": -1
  },
  {
    "appid": 1222870,
    "peak_count": -1
  },
  {
    "appid": 1222940,
    "peak_count": 5
  },
  {
    "appid": 1222980,
    "peak_count": -1
  },
  {
    "appid": 1223020,
    "peak_count": 118
  },
  {
    "appid": 1223090,
    "peak_count": -1
  },
  {
    "appid": 1223110,
    "peak_count": -1
  },
  {
    "appid": 1223160,
    "peak_count": -1
  },
  {
    "appid": 1223210,
    "peak_count": -1
  },
  {
    "appid": 1223260,
    "peak_count": 3
  },
  {
    "appid": 1223270,
    "peak_count": -1
  },
  {
    "appid": 1223350,
    "peak_count": -1
  },
  {
    "appid": 1223370,
    "peak_count": -1
  },
  {
    "appid": 1223380,
    "peak_count": -1
  },
  {
    "appid": 1223390,
    "peak_count": -1
  },
  {
    "appid": 1223500,
    "peak_count": 44
  },
  {
    "appid": 1223550,
    "peak_count": -1
  },
  {
    "appid": 1223660,
    "peak_count": -1
  },
  {
    "appid": 1223670,
    "peak_count": -1
  },
  {
    "appid": 1223680,
    "peak_count": -1
  },
  {
    "appid": 1223760,
    "peak_count": -1
  },
  {
    "appid": 1223870,
    "peak_count": 124
  },
  {
    "appid": 1223880,
    "peak_count": -1
  },
  {
    "appid": 1223910,
    "peak_count": 98
  },
  {
    "appid": 1224010,
    "peak_count": -1
  },
  {
    "appid": 1224020,
    "peak_count": 93
  },
  {
    "appid": 1224050,
    "peak_count": -1
  },
  {
    "appid": 1224120,
    "peak_count": -1
  },
  {
    "appid": 1224130,
    "peak_count": -1
  },
  {
    "appid": 1224290,
    "peak_count": 133
  },
  {
    "appid": 1224320,
    "peak_count": -1
  },
  {
    "appid": 1224380,
    "peak_count": -1
  },
  {
    "appid": 1224420,
    "peak_count": -1
  },
  {
    "appid": 1224450,
    "peak_count": 8
  },
  {
    "appid": 1224470,
    "peak_count": -1
  },
  {
    "appid": 1224480,
    "peak_count": -1
  },
  {
    "appid": 1224490,
    "peak_count": 1
  },
  {
    "appid": 1224530,
    "peak_count": -1
  },
  {
    "appid": 1224600,
    "peak_count": -1
  },
  {
    "appid": 1224640,
    "peak_count": -1
  },
  {
    "appid": 1224650,
    "peak_count": -1
  },
  {
    "appid": 1224710,
    "peak_count": -1
  },
  {
    "appid": 1224720,
    "peak_count": -1
  },
  {
    "appid": 1224840,
    "peak_count": 7
  },
  {
    "appid": 1224900,
    "peak_count": -1
  },
  {
    "appid": 1225040,
    "peak_count": -1
  },
  {
    "appid": 1225070,
    "peak_count": 24
  },
  {
    "appid": 1225100,
    "peak_count": -1
  },
  {
    "appid": 1225110,
    "peak_count": -1
  },
  {
    "appid": 1225120,
    "peak_count": -1
  },
  {
    "appid": 1225130,
    "peak_count": -1
  },
  {
    "appid": 1225220,
    "peak_count": 2
  },
  {
    "appid": 1225240,
    "peak_count": -1
  },
  {
    "appid": 1225290,
    "peak_count": 2
  },
  {
    "appid": 1225330,
    "peak_count": 31311
  },
  {
    "appid": 1225370,
    "peak_count": -1
  },
  {
    "appid": 1225380,
    "peak_count": -1
  },
  {
    "appid": 1225550,
    "peak_count": -1
  },
  {
    "appid": 1225560,
    "peak_count": 327
  },
  {
    "appid": 1225570,
    "peak_count": 895
  },
  {
    "appid": 1225580,
    "peak_count": -1
  },
  {
    "appid": 1225590,
    "peak_count": 82
  },
  {
    "appid": 1225600,
    "peak_count": -1
  },
  {
    "appid": 1225610,
    "peak_count": -1
  },
  {
    "appid": 1225640,
    "peak_count": -1
  },
  {
    "appid": 1225660,
    "peak_count": -1
  },
  {
    "appid": 1225680,
    "peak_count": -1
  },
  {
    "appid": 1225710,
    "peak_count": -1
  },
  {
    "appid": 1225780,
    "peak_count": 232
  },
  {
    "appid": 1225790,
    "peak_count": -1
  },
  {
    "appid": 1225810,
    "peak_count": -1
  },
  {
    "appid": 1225820,
    "peak_count": -1
  },
  {
    "appid": 1225840,
    "peak_count": 4
  },
  {
    "appid": 1225850,
    "peak_count": -1
  },
  {
    "appid": 1225910,
    "peak_count": -1
  },
  {
    "appid": 1225920,
    "peak_count": -1
  },
  {
    "appid": 1225930,
    "peak_count": 1
  },
  {
    "appid": 1225940,
    "peak_count": 1
  },
  {
    "appid": 1225980,
    "peak_count": -1
  },
  {
    "appid": 1226000,
    "peak_count": -1
  },
  {
    "appid": 1226010,
    "peak_count": 7
  },
  {
    "appid": 1226020,
    "peak_count": -1
  },
  {
    "appid": 1226070,
    "peak_count": -1
  },
  {
    "appid": 1226170,
    "peak_count": -1
  },
  {
    "appid": 1226180,
    "peak_count": 0
  },
  {
    "appid": 1226210,
    "peak_count": -1
  },
  {
    "appid": 1226230,
    "peak_count": -1
  },
  {
    "appid": 1226250,
    "peak_count": -1
  },
  {
    "appid": 1226420,
    "peak_count": -1
  },
  {
    "appid": 1226470,
    "peak_count": -1
  },
  {
    "appid": 1226490,
    "peak_count": -1
  },
  {
    "appid": 1226510,
    "peak_count": 1680
  },
  {
    "appid": 1226530,
    "peak_count": -1
  },
  {
    "appid": 1226610,
    "peak_count": -1
  },
  {
    "appid": 1226690,
    "peak_count": -1
  },
  {
    "appid": 1226760,
    "peak_count": -1
  },
  {
    "appid": 1226820,
    "peak_count": 0
  },
  {
    "appid": 1226840,
    "peak_count": -1
  },
  {
    "appid": 1226890,
    "peak_count": -1
  },
  {
    "appid": 1226920,
    "peak_count": -1
  },
  {
    "appid": 1226940,
    "peak_count": -1
  },
  {
    "appid": 1226960,
    "peak_count": -1
  },
  {
    "appid": 1226990,
    "peak_count": -1
  },
  {
    "appid": 1227000,
    "peak_count": 2
  },
  {
    "appid": 1227010,
    "peak_count": 2
  },
  {
    "appid": 1227050,
    "peak_count": -1
  },
  {
    "appid": 1227090,
    "peak_count": 1
  },
  {
    "appid": 1227130,
    "peak_count": 1
  },
  {
    "appid": 1227150,
    "peak_count": -1
  },
  {
    "appid": 1227160,
    "peak_count": -1
  },
  {
    "appid": 1227190,
    "peak_count": -1
  },
  {
    "appid": 1227250,
    "peak_count": -1
  },
  {
    "appid": 1227260,
    "peak_count": -1
  },
  {
    "appid": 1227280,
    "peak_count": 1447
  },
  {
    "appid": 1227320,
    "peak_count": 7
  },
  {
    "appid": 1227360,
    "peak_count": -1
  },
  {
    "appid": 1227390,
    "peak_count": -1
  },
  {
    "appid": 1227400,
    "peak_count": -1
  },
  {
    "appid": 1227530,
    "peak_count": 3051
  },
  {
    "appid": 1227570,
    "peak_count": -1
  },
  {
    "appid": 1227580,
    "peak_count": -1
  },
  {
    "appid": 1227650,
    "peak_count": 185
  },
  {
    "appid": 1227690,
    "peak_count": 324
  },
  {
    "appid": 1227730,
    "peak_count": 2
  },
  {
    "appid": 1227740,
    "peak_count": -1
  },
  {
    "appid": 1227750,
    "peak_count": -1
  },
  {
    "appid": 1227760,
    "peak_count": -1
  },
  {
    "appid": 1227780,
    "peak_count": 629
  },
  {
    "appid": 1227800,
    "peak_count": -1
  },
  {
    "appid": 1227830,
    "peak_count": -1
  },
  {
    "appid": 1227860,
    "peak_count": -1
  },
  {
    "appid": 1227890,
    "peak_count": 4903
  },
  {
    "appid": 1227900,
    "peak_count": -1
  },
  {
    "appid": 1227910,
    "peak_count": -1
  },
  {
    "appid": 1227930,
    "peak_count": -1
  },
  {
    "appid": 1228320,
    "peak_count": -1
  },
  {
    "appid": 1228330,
    "peak_count": -1
  },
  {
    "appid": 1228410,
    "peak_count": 9
  },
  {
    "appid": 1228430,
    "peak_count": -1
  },
  {
    "appid": 1228450,
    "peak_count": 0
  },
  {
    "appid": 1228470,
    "peak_count": -1
  },
  {
    "appid": 1228490,
    "peak_count": -1
  },
  {
    "appid": 1228500,
    "peak_count": -1
  },
  {
    "appid": 1228510,
    "peak_count": 10
  },
  {
    "appid": 1228520,
    "peak_count": 129
  },
  {
    "appid": 1228560,
    "peak_count": -1
  },
  {
    "appid": 1228570,
    "peak_count": 11
  },
  {
    "appid": 1228600,
    "peak_count": -1
  },
  {
    "appid": 1228630,
    "peak_count": 2
  },
  {
    "appid": 1228670,
    "peak_count": -1
  },
  {
    "appid": 1228680,
    "peak_count": 1
  },
  {
    "appid": 1228700,
    "peak_count": -1
  },
  {
    "appid": 1228730,
    "peak_count": -1
  },
  {
    "appid": 1228760,
    "peak_count": 4
  },
  {
    "appid": 1228790,
    "peak_count": -1
  },
  {
    "appid": 1228820,
    "peak_count": -1
  },
  {
    "appid": 1228840,
    "peak_count": -1
  },
  {
    "appid": 1228860,
    "peak_count": -1
  },
  {
    "appid": 1228870,
    "peak_count": -1
  },
  {
    "appid": 1228880,
    "peak_count": -1
  },
  {
    "appid": 1228910,
    "peak_count": -1
  },
  {
    "appid": 1228920,
    "peak_count": -1
  },
  {
    "appid": 1228950,
    "peak_count": 1
  },
  {
    "appid": 1228960,
    "peak_count": -1
  },
  {
    "appid": 1228970,
    "peak_count": -1
  },
  {
    "appid": 1229010,
    "peak_count": -1
  },
  {
    "appid": 1229030,
    "peak_count": -1
  },
  {
    "appid": 1229060,
    "peak_count": -1
  },
  {
    "appid": 1229190,
    "peak_count": -1
  },
  {
    "appid": 1229200,
    "peak_count": -1
  },
  {
    "appid": 1229250,
    "peak_count": -1
  },
  {
    "appid": 1229270,
    "peak_count": 9
  },
  {
    "appid": 1229280,
    "peak_count": -1
  },
  {
    "appid": 1229310,
    "peak_count": -1
  },
  {
    "appid": 1229380,
    "peak_count": 799
  },
  {
    "appid": 1229390,
    "peak_count": 12
  },
  {
    "appid": 1229420,
    "peak_count": 270
  },
  {
    "appid": 1229450,
    "peak_count": -1
  },
  {
    "appid": 1229460,
    "peak_count": 940
  },
  {
    "appid": 1229490,
    "peak_count": 16093
  },
  {
    "appid": 1229570,
    "peak_count": 18
  },
  {
    "appid": 1229580,
    "peak_count": 177
  },
  {
    "appid": 1229590,
    "peak_count": -1
  },
  {
    "appid": 1229640,
    "peak_count": 1
  },
  {
    "appid": 1229650,
    "peak_count": -1
  },
  {
    "appid": 1229720,
    "peak_count": -1
  },
  {
    "appid": 1229730,
    "peak_count": -1
  },
  {
    "appid": 1229740,
    "peak_count": -1
  },
  {
    "appid": 1229880,
    "peak_count": -1
  },
  {
    "appid": 1229900,
    "peak_count": 1379
  },
  {
    "appid": 1229960,
    "peak_count": -1
  },
  {
    "appid": 1230010,
    "peak_count": 1
  },
  {
    "appid": 1230020,
    "peak_count": 1
  },
  {
    "appid": 1230100,
    "peak_count": -1
  },
  {
    "appid": 1230120,
    "peak_count": -1
  },
  {
    "appid": 1230140,
    "peak_count": 448
  },
  {
    "appid": 1230200,
    "peak_count": -1
  },
  {
    "appid": 1230210,
    "peak_count": -1
  },
  {
    "appid": 1230410,
    "peak_count": 134
  },
  {
    "appid": 1230430,
    "peak_count": -1
  },
  {
    "appid": 1230510,
    "peak_count": -1
  },
  {
    "appid": 1230560,
    "peak_count": 62
  },
  {
    "appid": 1230570,
    "peak_count": -1
  },
  {
    "appid": 1230650,
    "peak_count": -1
  },
  {
    "appid": 1230660,
    "peak_count": -1
  },
  {
    "appid": 1230790,
    "peak_count": -1
  },
  {
    "appid": 1230800,
    "peak_count": 37
  },
  {
    "appid": 1230840,
    "peak_count": -1
  },
  {
    "appid": 1230860,
    "peak_count": 15
  },
  {
    "appid": 1230870,
    "peak_count": -1
  },
  {
    "appid": 1230880,
    "peak_count": -1
  },
  {
    "appid": 1230930,
    "peak_count": -1
  },
  {
    "appid": 1230990,
    "peak_count": 5
  },
  {
    "appid": 12310,
    "peak_count": 7
  },
  {
    "appid": 1231000,
    "peak_count": -1
  },
  {
    "appid": 1231040,
    "peak_count": -1
  },
  {
    "appid": 1231090,
    "peak_count": -1
  },
  {
    "appid": 1231100,
    "peak_count": -1
  },
  {
    "appid": 1231120,
    "peak_count": -1
  },
  {
    "appid": 1231130,
    "peak_count": -1
  },
  {
    "appid": 1231180,
    "peak_count": -1
  },
  {
    "appid": 1231190,
    "peak_count": -1
  },
  {
    "appid": 1231270,
    "peak_count": -1
  },
  {
    "appid": 1231440,
    "peak_count": -1
  },
  {
    "appid": 1231460,
    "peak_count": 92
  },
  {
    "appid": 1231520,
    "peak_count": 99
  },
  {
    "appid": 1231530,
    "peak_count": -1
  },
  {
    "appid": 1231540,
    "peak_count": -1
  },
  {
    "appid": 1231570,
    "peak_count": -1
  },
  {
    "appid": 1231590,
    "peak_count": 491
  },
  {
    "appid": 1231640,
    "peak_count": -1
  },
  {
    "appid": 1231670,
    "peak_count": -1
  },
  {
    "appid": 1231720,
    "peak_count": 0
  },
  {
    "appid": 1231740,
    "peak_count": 1
  },
  {
    "appid": 1231750,
    "peak_count": -1
  },
  {
    "appid": 1231760,
    "peak_count": 3
  },
  {
    "appid": 1231770,
    "peak_count": -1
  },
  {
    "appid": 1231780,
    "peak_count": -1
  },
  {
    "appid": 1231800,
    "peak_count": 2
  },
  {
    "appid": 1231810,
    "peak_count": 3
  },
  {
    "appid": 1231820,
    "peak_count": -1
  },
  {
    "appid": 1231880,
    "peak_count": 407
  },
  {
    "appid": 1231900,
    "peak_count": -1
  },
  {
    "appid": 1231920,
    "peak_count": -1
  },
  {
    "appid": 1231940,
    "peak_count": -1
  },
  {
    "appid": 1231950,
    "peak_count": 23
  },
  {
    "appid": 1231970,
    "peak_count": -1
  },
  {
    "appid": 12320,
    "peak_count": 192
  },
  {
    "appid": 1232010,
    "peak_count": 10
  },
  {
    "appid": 1232100,
    "peak_count": -1
  },
  {
    "appid": 1232120,
    "peak_count": -1
  },
  {
    "appid": 1232130,
    "peak_count": 523
  },
  {
    "appid": 1232140,
    "peak_count": -1
  },
  {
    "appid": 1232150,
    "peak_count": -1
  },
  {
    "appid": 1232180,
    "peak_count": 140
  },
  {
    "appid": 1232230,
    "peak_count": 2
  },
  {
    "appid": 1232260,
    "peak_count": -1
  },
  {
    "appid": 1232290,
    "peak_count": -1
  },
  {
    "appid": 1232310,
    "peak_count": -1
  },
  {
    "appid": 1232410,
    "peak_count": 6
  },
  {
    "appid": 1232420,
    "peak_count": 1749
  },
  {
    "appid": 1232430,
    "peak_count": -1
  },
  {
    "appid": 1232460,
    "peak_count": 164
  },
  {
    "appid": 1232510,
    "peak_count": -1
  },
  {
    "appid": 1232580,
    "peak_count": 70
  },
  {
    "appid": 1232590,
    "peak_count": -1
  },
  {
    "appid": 1232610,
    "peak_count": -1
  },
  {
    "appid": 1232640,
    "peak_count": 12
  },
  {
    "appid": 1232650,
    "peak_count": -1
  },
  {
    "appid": 1232670,
    "peak_count": -1
  },
  {
    "appid": 1232710,
    "peak_count": -1
  },
  {
    "appid": 1232730,
    "peak_count": -1
  },
  {
    "appid": 1232810,
    "peak_count": -1
  },
  {
    "appid": 1232830,
    "peak_count": -1
  },
  {
    "appid": 1232890,
    "peak_count": -1
  },
  {
    "appid": 1232920,
    "peak_count": 1
  },
  {
    "appid": 1232940,
    "peak_count": -1
  },
  {
    "appid": 1232980,
    "peak_count": -1
  },
  {
    "appid": 12330,
    "peak_count": 74
  },
  {
    "appid": 1233020,
    "peak_count": -1
  },
  {
    "appid": 1233030,
    "peak_count": -1
  },
  {
    "appid": 1233040,
    "peak_count": -1
  },
  {
    "appid": 1233120,
    "peak_count": -1
  },
  {
    "appid": 1233170,
    "peak_count": -1
  },
  {
    "appid": 1233200,
    "peak_count": -1
  },
  {
    "appid": 1233230,
    "peak_count": -1
  },
  {
    "appid": 1233240,
    "peak_count": -1
  },
  {
    "appid": 1233250,
    "peak_count": -1
  },
  {
    "appid": 1233260,
    "peak_count": 1923
  },
  {
    "appid": 1233270,
    "peak_count": 1016
  },
  {
    "appid": 1233350,
    "peak_count": -1
  },
  {
    "appid": 1233410,
    "peak_count": 23
  },
  {
    "appid": 1233420,
    "peak_count": -1
  },
  {
    "appid": 1233460,
    "peak_count": -1
  },
  {
    "appid": 1233510,
    "peak_count": -1
  },
  {
    "appid": 1233530,
    "peak_count": -1
  },
  {
    "appid": 1233540,
    "peak_count": 13
  },
  {
    "appid": 1233550,
    "peak_count": -1
  },
  {
    "appid": 1233570,
    "peak_count": 1427
  },
  {
    "appid": 1233580,
    "peak_count": -1
  },
  {
    "appid": 1233590,
    "peak_count": -1
  },
  {
    "appid": 1233610,
    "peak_count": -1
  },
  {
    "appid": 1233690,
    "peak_count": 11
  },
  {
    "appid": 1233720,
    "peak_count": -1
  },
  {
    "appid": 1233780,
    "peak_count": -1
  },
  {
    "appid": 1233790,
    "peak_count": -1
  },
  {
    "appid": 1233800,
    "peak_count": 32
  },
  {
    "appid": 1233820,
    "peak_count": -1
  },
  {
    "appid": 1233850,
    "peak_count": 4
  },
  {
    "appid": 1233880,
    "peak_count": 592
  },
  {
    "appid": 1233990,
    "peak_count": -1
  },
  {
    "appid": 12340,
    "peak_count": -1
  },
  {
    "appid": 1234020,
    "peak_count": -1
  },
  {
    "appid": 1234030,
    "peak_count": -1
  },
  {
    "appid": 1234060,
    "peak_count": -1
  },
  {
    "appid": 1234070,
    "peak_count": -1
  },
  {
    "appid": 1234110,
    "peak_count": -1
  },
  {
    "appid": 1234120,
    "peak_count": -1
  },
  {
    "appid": 1234160,
    "peak_count": -1
  },
  {
    "appid": 1234190,
    "peak_count": 11
  },
  {
    "appid": 1234220,
    "peak_count": 15
  },
  {
    "appid": 1234240,
    "peak_count": 15
  },
  {
    "appid": 1234260,
    "peak_count": -1
  },
  {
    "appid": 1234290,
    "peak_count": -1
  },
  {
    "appid": 1234340,
    "peak_count": -1
  },
  {
    "appid": 1234360,
    "peak_count": 0
  },
  {
    "appid": 1234380,
    "peak_count": -1
  },
  {
    "appid": 1234400,
    "peak_count": -1
  },
  {
    "appid": 1234450,
    "peak_count": -1
  },
  {
    "appid": 1234500,
    "peak_count": -1
  },
  {
    "appid": 1234520,
    "peak_count": -1
  },
  {
    "appid": 1234540,
    "peak_count": 1
  },
  {
    "appid": 1234580,
    "peak_count": -1
  },
  {
    "appid": 1234590,
    "peak_count": 1
  }
]