[
  {
    "appid": 1234600,
    "peak_count": 1
  },
  {
    "appid": 1234620,
    "peak_count": 12
  },
  {
    "appid": 1234630,
    "peak_count": 1
  },
  {
    "appid": 1234690,
    "peak_count": -1
  },
  {
    "appid": 1234700,
    "peak_count": 2
  },
  {
    "appid": 1234730,
    "peak_count": 30
  },
  {
    "appid": 1234750,
    "peak_count": -1
  },
  {
    "appid": 1234820,
    "peak_count": 0
  },
  {
    "appid": 1234830,
    "peak_count": -1
  },
  {
    "appid": 1234850,
    "peak_count": -1
  },
  {
    "appid": 1234890,
    "peak_count": -1
  },
  {
    "appid": 1234900,
    "peak_count": 1
  },
  {
    "appid": 1234930,
    "peak_count": -1
  },
  {
    "appid": 1234940,
    "peak_count": 275
  },
  {
    "appid": 1234980,
    "peak_count": -1
  },
  {
    "appid": 1235110,
    "peak_count": 122
  },
  {
    "appid": 1235120,
    "peak_count": -1
  },
  {
    "appid": 1235130,
    "peak_count": -1
  },
  {
    "appid": 1235140,
    "peak_count": 9508
  },
  {
    "appid": 1235160,
    "peak_count": -1
  },
  {
    "appid": 1235220,
    "peak_count": -1
  },
  {
    "appid": 1235310,
    "peak_count": -1
  },
  {
    "appid": 1235350,
    "peak_count": 4
  },
  {
    "appid": 1235360,
    "peak_count": 22
  },
  {
    "appid": 1235430,
    "peak_count": 1
  },
  {
    "appid": 1235440,
    "peak_count": 0
  },
  {
    "appid": 1235450,
    "peak_count": 7
  },
  {
    "appid": 1235460,
    "peak_count": 2
  },
  {
    "appid": 1235480,
    "peak_count": -1
  },
  {
    "appid": 1235510,
    "peak_count": -1
  },
  {
    "appid": 1235570,
    "peak_count": -1
  },
  {
    "appid": 1235770,
    "peak_count": -1
  },
  {
    "appid": 1235790,
    "peak_count": -1
  },
  {
    "appid": 1235800,
    "peak_count": -1
  },
  {
    "appid": 1235810,
    "peak_count": 1
  },
  {
    "appid": 1235830,
    "peak_count": -1
  },
  {
    "appid": 1235920,
    "peak_count": -1
  },
  {
    "appid": 1235980,
    "peak_count": 1
  },
  {
    "appid": 12360,
    "peak_count": 168
  },
  {
    "appid": 1236000,
    "peak_count": -1
  },
  {
    "appid": 1236040,
    "peak_count": 10
  },
  {
    "appid": 1236050,
    "peak_count": -1
  },
  {
    "appid": 1236070,
    "peak_count": -1
  },
  {
    "appid": 1236160,
    "peak_count": -1
  },
  {
    "appid": 1236180,
    "peak_count": -1
  },
  {
    "appid": 1236190,
    "peak_count": -1
  },
  {
    "appid": 1236240,
    "peak_count": 246
  },
  {
    "appid": 1236300,
    "peak_count": 2080
  },
  {
    "appid": 1236320,
    "peak_count": 4
  },
  {
    "appid": 1236330,
    "peak_count": -1
  },
  {
    "appid": 1236390,
    "peak_count": 506
  },
  {
    "appid": 1236450,
    "peak_count": 15
  },
  {
    "appid": 1236470,
    "peak_count": -1
  },
  {
    "appid": 1236480,
    "peak_count": -1
  },
  {
    "appid": 1236490,
    "peak_count": -1
  },
  {
    "appid": 1236530,
    "peak_count": 13
  },
  {
    "appid": 1236560,
    "peak_count": -1
  },
  {
    "appid": 1236620,
    "peak_count": -1
  },
  {
    "appid": 1236670,
    "peak_count": -1
  },
  {
    "appid": 1236760,
    "peak_count": -1
  },
  {
    "appid": 1236780,
    "peak_count": 60
  },
  {
    "appid": 1236810,
    "peak_count": -1
  },
  {
    "appid": 1236860,
    "peak_count": -1
  },
  {
    "appid": 1236880,
    "peak_count": -1
  },
  {
    "appid": 1236900,
    "peak_count": 9
  },
  {
    "appid": 1236960,
    "peak_count": -1
  },
  {
    "appid": 1236990,
    "peak_count": 661
  },
  {
    "appid": 1237050,
    "peak_count": -1
  },
  {
    "appid": 1237060,
    "peak_count": 1
  },
  {
    "appid": 1237070,
    "peak_count": -1
  },
  {
    "appid": 1237080,
    "peak_count": -1
  },
  {
    "appid": 1237090,
    "peak_count": -1
  },
  {
    "appid": 1237110,
    "peak_count": -1
  },
  {
    "appid": 1237120,
    "peak_count": 0
  },
  {
    "appid": 1237170,
    "peak_count": -1
  },
  {
    "appid": 1237210,
    "peak_count": 1
  },
  {
    "appid": 1237240,
    "peak_count": -1
  },
  {
    "appid": 1237260,
    "peak_count": -1
  },
  {
    "appid": 1237310,
    "peak_count": -1
  },
  {
    "appid": 1237330,
    "peak_count": -1
  },
  {
    "appid": 1237410,
    "peak_count": 2
  },
  {
    "appid": 1237480,
    "peak_count": -1
  },
  {
    "appid": 1237490,
    "peak_count": -1
  },
  {
    "appid": 1237510,
    "peak_count": -1
  },
  {
    "appid": 1237540,
    "peak_count": -1
  },
  {
    "appid": 1237550,
    "peak_count": -1
  },
  {
    "appid": 1237560,
    "peak_count": -1
  },
  {
    "appid": 1237570,
    "peak_count": 1
  },
  {
    "appid": 1237590,
    "peak_count": -1
  },
  {
    "appid": 1237610,
    "peak_count": -1
  },
  {
    "appid": 1237670,
    "peak_count": -1
  },
  {
    "appid": 1237690,
    "peak_count": -1
  },
  {
    "appid": 1237700,
    "peak_count": -1
  },
  {
    "appid": 1237730,
    "peak_count": -1
  },
  {
    "appid": 1237760,
    "peak_count": -1
  },
  {
    "appid": 1237780,
    "peak_count": 3
  },
  {
    "appid": 1237800,
    "peak_count": -1
  },
  {
    "appid": 1237820,
    "peak_count": -1
  },
  {
    "appid": 1237840,
    "peak_count": -1
  },
  {
    "appid": 1237870,
    "peak_count": -1
  },
  {
    "appid": 1237880,
    "peak_count": -1
  },
  {
    "appid": 1237900,
    "peak_count": -1
  },
  {
    "appid": 1237950,
    "peak_count": 10345
  },
  {
    "appid": 1237970,
    "peak_count": 27547
  },
  {
    "appid": 1237980,
    "peak_count": 594
  },
  {
    "appid": 1238000,
    "peak_count": 3590
  },
  {
    "appid": 1238020,
    "peak_count": 659
  },
  {
    "appid": 1238040,
    "peak_count": 800
  },
  {
    "appid": 1238060,
    "peak_count": 1083
  },
  {
    "appid": 1238080,
    "peak_count": 588
  },
  {
    "appid": 1238180,
    "peak_count": 4
  },
  {
    "appid": 1238220,
    "peak_count": -1
  },
  {
    "appid": 1238250,
    "peak_count": 2
  },
  {
    "appid": 1238280,
    "peak_count": 114
  },
  {
    "appid": 1238320,
    "peak_count": -1
  },
  {
    "appid": 1238330,
    "peak_count": 17
  },
  {
    "appid": 1238360,
    "peak_count": -1
  },
  {
    "appid": 1238400,
    "peak_count": 8
  },
  {
    "appid": 1238470,
    "peak_count": -1
  },
  {
    "appid": 1238480,
    "peak_count": -1
  },
  {
    "appid": 1238490,
    "peak_count": -1
  },
  {
    "appid": 1238520,
    "peak_count": -1
  },
  {
    "appid": 1238540,
    "peak_count": -1
  },
  {
    "appid": 1238620,
    "peak_count": -1
  },
  {
    "appid": 1238630,
    "peak_count": 0
  },
  {
    "appid": 1238680,
    "peak_count": 63
  },
  {
    "appid": 1238710,
    "peak_count": -1
  },
  {
    "appid": 1238720,
    "peak_count": -1
  },
  {
    "appid": 1238730,
    "peak_count": 94
  },
  {
    "appid": 1238810,
    "peak_count": 89814
  },
  {
    "appid": 1238820,
    "peak_count": 480
  },
  {
    "appid": 1238840,
    "peak_count": 53107
  },
  {
    "appid": 1238860,
    "peak_count": 12342
  },
  {
    "appid": 1238880,
    "peak_count": 212
  },
  {
    "appid": 1238970,
    "peak_count": -1
  },
  {
    "appid": 1238980,
    "peak_count": -1
  },
  {
    "appid": 12390,
    "peak_count": -1
  },
  {
    "appid": 1239000,
    "peak_count": -1
  },
  {
    "appid": 1239020,
    "peak_count": 4229
  },
  {
    "appid": 1239030,
    "peak_count": -1
  },
  {
    "appid": 1239050,
    "peak_count": -1
  },
  {
    "appid": 1239080,
    "peak_count": 900
  },
  {
    "appid": 1239120,
    "peak_count": -1
  },
  {
    "appid": 1239140,
    "peak_count": -1
  },
  {
    "appid": 1239180,
    "peak_count": -1
  },
  {
    "appid": 1239260,
    "peak_count": 1607
  },
  {
    "appid": 1239270,
    "peak_count": -1
  },
  {
    "appid": 1239300,
    "peak_count": 2887
  },
  {
    "appid": 1239320,
    "peak_count": 1750
  },
  {
    "appid": 1239400,
    "peak_count": -1
  },
  {
    "appid": 1239430,
    "peak_count": -1
  },
  {
    "appid": 1239440,
    "peak_count": -1
  },
  {
    "appid": 1239490,
    "peak_count": -1
  },
  {
    "appid": 1239520,
    "peak_count": 3221
  },
  {
    "appid": 1239590,
    "peak_count": -1
  },
  {
    "appid": 1239660,
    "peak_count": -1
  },
  {
    "appid": 1239690,
    "peak_count": 638
  },
  {
    "appid": 1239740,
    "peak_count": -1
  },
  {
    "appid": 1239870,
    "peak_count": -1
  },
  {
    "appid": 1239900,
    "peak_count": -1
  },
  {
    "appid": 1239920,
    "peak_count": -1
  },
  {
    "appid": 1239970,
    "peak_count": -1
  },
  {
    "appid": 1239980,
    "peak_count": -1
  },
  {
    "appid": 1239990,
    "peak_count": 0
  },
  {
    "appid": 1240040,
    "peak_count": 3
  },
  {
    "appid": 1240050,
    "peak_count": 54
  },
  {
    "appid": 1240090,
    "peak_count": -1
  },
  {
    "appid": 1240120,
    "peak_count": -1
  },
  {
    "appid": 1240130,
    "peak_count": -1
  },
  {
    "appid": 1240140,
    "peak_count": 2
  },
  {
    "appid": 1240180,
    "peak_count": -1
  },
  {
    "appid": 1240210,
    "peak_count": 1327
  },
  {
    "appid": 1240230,
    "peak_count": 85
  },
  {
    "appid": 1240240,
    "peak_count": -1
  },
  {
    "appid": 1240270,
    "peak_count": 1
  },
  {
    "appid": 1240290,
    "peak_count": 158
  },
  {
    "appid": 1240350,
    "peak_count": -1
  },
  {
    "appid": 1240370,
    "peak_count": -1
  },
  {
    "appid": 1240440,
    "peak_count": 256619
  },
  {
    "appid": 1240460,
    "peak_count": -1
  },
  {
    "appid": 1240480,
    "peak_count": -1
  },
  {
    "appid": 1240490,
    "peak_count": -1
  },
  {
    "appid": 1240510,
    "peak_count": -1
  },
  {
    "appid": 1240530,
    "peak_count": -1
  },
  {
    "appid": 1240550,
    "peak_count": -1
  },
  {
    "appid": 1240600,
    "peak_count": -1
  },
  {
    "appid": 1240620,
    "peak_count": -1
  },
  {
    "appid": 1240630,
    "peak_count": 46
  },
  {
    "appid": 1240680,
    "peak_count": -1
  },
  {
    "appid": 1240690,
    "peak_count": -1
  },
  {
    "appid": 1240730,
    "peak_count": -1
  },
  {
    "appid": 1240790,
    "peak_count": -1
  },
  {
    "appid": 1240810,
    "peak_count": -1
  },
  {
    "appid": 1240840,
    "peak_count": -1
  },
  {
    "appid": 1241020,
    "peak_count": -1
  },
  {
    "appid": 1241030,
    "peak_count": -1
  },
  {
    "appid": 1241040,
    "peak_count": 82
  },
  {
    "appid": 1241100,
    "peak_count": 1208
  },
  {
    "appid": 1241110,
    "peak_count": -1
  },
  {
    "appid": 1241140,
    "peak_count": -1
  },
  {
    "appid": 1241160,
    "peak_count": 2
  },
  {
    "appid": 1241180,
    "peak_count": 1
  },
  {
    "appid": 1241230,
    "peak_count": -1
  },
  {
    "appid": 1241250,
    "peak_count": -1
  },
  {
    "appid": 1241370,
    "peak_count": -1
  },
  {
    "appid": 1241400,
    "peak_count": -1
  },
  {
    "appid": 1241440,
    "peak_count": -1
  },
  {
    "appid": 1241500,
    "peak_count": -1
  },
  {
    "appid": 1241510,
    "peak_count": -1
  },
  {
    "appid": 1241520,
    "peak_count": -1
  },
  {
    "appid": 1241690,
    "peak_count": -1
  },
  {
    "appid": 1241700,
    "peak_count": 153
  },
  {
    "appid": 1241710,
    "peak_count": -1
  },
  {
    "appid": 1241780,
    "peak_count": 1
  },
  {
    "appid": 1241810,
    "peak_count": -1
  },
  {
    "appid": 1241910,
    "peak_count": -1
  },
  {
    "appid": 1241950,
    "peak_count": 315
  },
  {
    "appid": 12420,
    "peak_count": -1
  },
  {
    "appid": 1242620,
    "peak_count": 4
  },
  {
    "appid": 1242630,
    "peak_count": 14
  },
  {
    "appid": 1242700,
    "peak_count": 1384
  },
  {
    "appid": 1242710,
    "peak_count": 22
  },
  {
    "appid": 1242730,
    "peak_count": -1
  },
  {
    "appid": 1242790,
    "peak_count": 3
  },
  {
    "appid": 1242800,
    "peak_count": -1
  },
  {
    "appid": 1242850,
    "peak_count": -1
  },
  {
    "appid": 1242910,
    "peak_count": -1
  },
  {
    "appid": 1242980,
    "peak_count": 338
  },
  {
    "appid": 12430,
    "peak_count": -1
  },
  {
    "appid": 1243010,
    "peak_count": -1
  },
  {
    "appid": 1243030,
    "peak_count": -1
  },
  {
    "appid": 1243040,
    "peak_count": 1
  },
  {
    "appid": 1243100,
    "peak_count": -1
  },
  {
    "appid": 1243130,
    "peak_count": -1
  },
  {
    "appid": 1243140,
    "peak_count": -1
  },
  {
    "appid": 1243150,
    "peak_count": 2
  },
  {
    "appid": 1243160,
    "peak_count": 6
  },
  {
    "appid": 1243200,
    "peak_count": -1
  },
  {
    "appid": 1243220,
    "peak_count": 105
  },
  {
    "appid": 1243240,
    "peak_count": -1
  },
  {
    "appid": 1243260,
    "peak_count": -1
  },
  {
    "appid": 1243290,
    "peak_count": -1
  },
  {
    "appid": 1243320,
    "peak_count": -1
  },
  {
    "appid": 1243360,
    "peak_count": -1
  },
  {
    "appid": 1243370,
    "peak_count": -1
  },
  {
    "appid": 1243450,
    "peak_count": -1
  },
  {
    "appid": 1243520,
    "peak_count": -1
  },
  {
    "appid": 1243530,
    "peak_count": -1
  },
  {
    "appid": 1243560,
    "peak_count": -1
  },
  {
    "appid": 1243580,
    "peak_count": -1
  },
  {
    "appid": 1243640,
    "peak_count": -1
  },
  {
    "appid": 1243670,
    "peak_count": 53
  },
  {
    "appid": 1243690,
    "peak_count": 19
  },
  {
    "appid": 1243700,
    "peak_count": -1
  },
  {
    "appid": 1243750,
    "peak_count": -1
  },
  {
    "appid": 1243790,
    "peak_count": 2
  },
  {
    "appid": 1243820,
    "peak_count": -1
  },
  {
    "appid": 1243830,
    "peak_count": 3077
  },
  {
    "appid": 1243880,
    "peak_count": -1
  },
  {
    "appid": 1243890,
    "peak_count": 100
  },
  {
    "appid": 1243900,
    "peak_count": 2
  },
  {
    "appid": 1243930,
    "peak_count": -1
  },
  {
    "appid": 1243960,
    "peak_count": 103
  },
  {
    "appid": 1244040,
    "peak_count": 15
  },
  {
    "appid": 1244050,
    "peak_count": -1
  },
  {
    "appid": 1244190,
    "peak_count": 1
  },
  {
    "appid": 1244210,
    "peak_count": -1
  },
  {
    "appid": 1244260,
    "peak_count": -1
  },
  {
    "appid": 1244300,
    "peak_count": 0
  },
  {
    "appid": 1244380,
    "peak_count": 14
  },
  {
    "appid": 1244390,
    "peak_count": -1
  },
  {
    "appid": 1244460,
    "peak_count": 17298
  },
  {
    "appid": 1244470,
    "peak_count": -1
  },
  {
    "appid": 1244520,
    "peak_count": -1
  },
  {
    "appid": 1244530,
    "peak_count": -1
  },
  {
    "appid": 1244630,
    "peak_count": 762
  },
  {
    "appid": 1244760,
    "peak_count": -1
  },
  {
    "appid": 1244770,
    "peak_count": -1
  },
  {
    "appid": 1244800,
    "peak_count": 894
  },
  {
    "appid": 1244830,
    "peak_count": -1
  },
  {
    "appid": 1244850,
    "peak_count": -1
  },
  {
    "appid": 1244860,
    "peak_count": -1
  },
  {
    "appid": 1244890,
    "peak_count": -1
  },
  {
    "appid": 1244930,
    "peak_count": 18
  },
  {
    "appid": 1244950,
    "peak_count": 551
  },
  {
    "appid": 1244960,
    "peak_count": 7
  },
  {
    "appid": 12450,
    "peak_count": -1
  },
  {
    "appid": 1245000,
    "peak_count": -1
  },
  {
    "appid": 1245060,
    "peak_count": -1
  },
  {
    "appid": 1245170,
    "peak_count": 1
  },
  {
    "appid": 1245260,
    "peak_count": 7
  },
  {
    "appid": 1245280,
    "peak_count": -1
  },
  {
    "appid": 1245350,
    "peak_count": 1
  },
  {
    "appid": 1245360,
    "peak_count": -1
  },
  {
    "appid": 1245370,
    "peak_count": -1
  },
  {
    "appid": 1245430,
    "peak_count": 154
  },
  {
    "appid": 1245470,
    "peak_count": 8
  },
  {
    "appid": 1245500,
    "peak_count": -1
  },
  {
    "appid": 1245540,
    "peak_count": 135
  },
  {
    "appid": 1245550,
    "peak_count": -1
  },
  {
    "appid": 1245570,
    "peak_count": -1
  },
  {
    "appid": 1245600,
    "peak_count": -1
  },
  {
    "appid": 1245620,
    "peak_count": 952523
  },
  {
    "appid": 1245630,
    "peak_count": -1
  },
  {
    "appid": 1245640,
    "peak_count": 5
  },
  {
    "appid": 1245660,
    "peak_count": -1
  },
  {
    "appid": 1245670,
    "peak_count": 46
  },
  {
    "appid": 1245730,
    "peak_count": -1
  },
  {
    "appid": 1245810,
    "peak_count": -1
  },
  {
    "appid": 1245820,
    "peak_count": 7
  },
  {
    "appid": 1245900,
    "peak_count": 1
  },
  {
    "appid": 1245920,
    "peak_count": -1
  },
  {
    "appid": 1245930,
    "peak_count": -1
  },
  {
    "appid": 1245950,
    "peak_count": 25
  },
  {
    "appid": 1245980,
    "peak_count": 0
  },
  {
    "appid": 12460,
    "peak_count": -1
  },
  {
    "appid": 1246020,
    "peak_count": 146
  },
  {
    "appid": 1246040,
    "peak_count": -1
  },
  {
    "appid": 1246060,
    "peak_count": -1
  },
  {
    "appid": 1246120,
    "peak_count": 0
  },
  {
    "appid": 1246140,
    "peak_count": -1
  },
  {
    "appid": 1246170,
    "peak_count": -1
  },
  {
    "appid": 1246200,
    "peak_count": -1
  },
  {
    "appid": 1246230,
    "peak_count": 3
  },
  {
    "appid": 1246250,
    "peak_count": -1
  },
  {
    "appid": 1246320,
    "peak_count": -1
  },
  {
    "appid": 1246420,
    "peak_count": 2
  },
  {
    "appid": 1246460,
    "peak_count": 2
  },
  {
    "appid": 1246490,
    "peak_count": -1
  },
  {
    "appid": 1246540,
    "peak_count": -1
  },
  {
    "appid": 1246600,
    "peak_count": -1
  },
  {
    "appid": 1246620,
    "peak_count": 1
  },
  {
    "appid": 1246650,
    "peak_count": -1
  },
  {
    "appid": 1246680,
    "peak_count": 1
  },
  {
    "appid": 1246710,
    "peak_count": -1
  },
  {
    "appid": 1246870,
    "peak_count": 28
  },
  {
    "appid": 1246880,
    "peak_count": 13
  },
  {
    "appid": 1246930,
    "peak_count": 27
  },
  {
    "appid": 1246940,
    "peak_count": 8
  },
  {
    "appid": 1246950,
    "peak_count": -1
  },
  {
    "appid": 12470,
    "peak_count": 73
  },
  {
    "appid": 1247020,
    "peak_count": -1
  },
  {
    "appid": 1247030,
    "peak_count": -1
  },
  {
    "appid": 1247100,
    "peak_count": -1
  },
  {
    "appid": 1247110,
    "peak_count": 14
  },
  {
    "appid": 1247170,
    "peak_count": -1
  },
  {
    "appid": 1247210,
    "peak_count": 3
  },
  {
    "appid": 1247240,
    "peak_count": -1
  },
  {
    "appid": 1247290,
    "peak_count": 35
  },
  {
    "appid": 1247360,
    "peak_count": 43
  },
  {
    "appid": 1247370,
    "peak_count": -1
  },
  {
    "appid": 1247400,
    "peak_count": -1
  },
  {
    "appid": 1247460,
    "peak_count": -1
  },
  {
    "appid": 1247570,
    "peak_count": -1
  },
  {
    "appid": 1247580,
    "peak_count": 2
  },
  {
    "appid": 1247640,
    "peak_count": -1
  },
  {
    "appid": 1247650,
    "peak_count": 3
  },
  {
    "appid": 1247720,
    "peak_count": 6
  },
  {
    "appid": 1247730,
    "peak_count": 1
  },
  {
    "appid": 1247830,
    "peak_count": 2
  },
  {
    "appid": 1247860,
    "peak_count": -1
  },
  {
    "appid": 1247870,
    "peak_count": 1
  },
  {
    "appid": 1247880,
    "peak_count": -1
  },
  {
    "appid": 1247910,
    "peak_count": -1
  },
  {
    "appid": 1247920,
    "peak_count": -1
  },
  {
    "appid": 1247940,
    "peak_count": -1
  },
  {
    "appid": 1247950,
    "peak_count": -1
  },
  {
    "appid": 12480,
    "peak_count": -1
  },
  {
    "appid": 1248030,
    "peak_count": -1
  },
  {
    "appid": 1248060,
    "peak_count": 254
  },
  {
    "appid": 1248100,
    "peak_count": -1
  },
  {
    "appid": 1248120,
    "peak_count": -1
  },
  {
    "appid": 1248130,
    "peak_count": 96402
  },
  {
    "appid": 1248140,
    "peak_count": -1
  },
  {
    "appid": 1248150,
    "peak_count": -1
  },
  {
    "appid": 1248240,
    "peak_count": -1
  },
  {
    "appid": 1248270,
    "peak_count": 8
  },
  {
    "appid": 1248350,
    "peak_count": 2
  },
  {
    "appid": 1248360,
    "peak_count": -1
  },
  {
    "appid": 1248370,
    "peak_count": -1
  },
  {
    "appid": 1248390,
    "peak_count": -1
  },
  {
    "appid": 1248450,
    "peak_count": -1
  },
  {
    "appid": 1248460,
    "peak_count": -1
  },
  {
    "appid": 1248490,
    "peak_count": -1
  },
  {
    "appid": 1248510,
    "peak_count": -1
  },
  {
    "appid": 1248550,
    "peak_count": -1
  },
  {
    "appid": 1248570,
    "peak_count": -1
  },
  {
    "appid": 1248590,
    "peak_count": 16
  },
  {
    "appid": 1248650,
    "peak_count": -1
  },
  {
    "appid": 1248670,
    "peak_count": -1
  },
  {
    "appid": 1248680,
    "peak_count": 2
  },
  {
    "appid": 1248710,
    "peak_count": -1
  },
  {
    "appid": 1248730,
    "peak_count": -1
  },
  {
    "appid": 1248740,
    "peak_count": 6
  },
  {
    "appid": 1248800,
    "peak_count": -1
  },
  {
    "appid": 1248810,
    "peak_count": -1
  },
  {
    "appid": 1248820,
    "peak_count": -1
  },
  {
    "appid": 1248840,
    "peak_count": 35
  },
  {
    "appid": 1248860,
    "peak_count": -1
  },
  {
    "appid": 1248870,
    "peak_count": -1
  },
  {
    "appid": 1248910,
    "peak_count": -1
  },
  {
    "appid": 1248960,
    "peak_count": 1
  },
  {
    "appid": 1248990,
    "peak_count": 100
  },
  {
    "appid": 1249010,
    "peak_count": -1
  },
  {
    "appid": 1249060,
    "peak_count": -1
  },
  {
    "appid": 1249070,
    "peak_count": -1
  },
  {
    "appid": 1249080,
    "peak_count": -1
  },
  {
    "appid": 1249110,
    "peak_count": -1
  },
  {
    "appid": 1249130,
    "peak_count": 124
  },
  {
    "appid": 1249150,
    "peak_count": -1
  },
  {
    "appid": 1249170,
    "peak_count": -1
  },
  {
    "appid": 1249190,
    "peak_count": -1
  },
  {
    "appid": 1249260,
    "peak_count": 27
  },
  {
    "appid": 1249290,
    "peak_count": -1
  },
  {
    "appid": 1249300,
    "peak_count": -1
  },
  {
    "appid": 1249390,
    "peak_count": -1
  },
  {
    "appid": 1249410,
    "peak_count": 3
  },
  {
    "appid": 1249420,
    "peak_count": -1
  },
  {
    "appid": 1249430,
    "peak_count": -1
  },
  {
    "appid": 1249480,
    "peak_count": -1
  },
  {
    "appid": 1249500,
    "peak_count": 4
  },
  {
    "appid": 1249510,
    "peak_count": -1
  },
  {
    "appid": 1249620,
    "peak_count": 0
  },
  {
    "appid": 1249680,
    "peak_count": -1
  },
  {
    "appid": 1249740,
    "peak_count": -1
  },
  {
    "appid": 1249800,
    "peak_count": 11772
  },
  {
    "appid": 1249850,
    "peak_count": -1
  },
  {
    "appid": 1249890,
    "peak_count": 4
  },
  {
    "appid": 1249980,
    "peak_count": -1
  },
  {
    "appid": 1250,
    "peak_count": 21151
  },
  {
    "appid": 12500,
    "peak_count": 610
  },
  {
    "appid": 1250030,
    "peak_count": -1
  },
  {
    "appid": 1250040,
    "peak_count": -1
  },
  {
    "appid": 1250060,
    "peak_count": -1
  },
  {
    "appid": 1250070,
    "peak_count": -1
  },
  {
    "appid": 1250100,
    "peak_count": 16
  },
  {
    "appid": 1250120,
    "peak_count": -1
  },
  {
    "appid": 1250170,
    "peak_count": -1
  },
  {
    "appid": 1250210,
    "peak_count": -1
  },
  {
    "appid": 1250220,
    "peak_count": -1
  },
  {
    "appid": 1250240,
    "peak_count": -1
  },
  {
    "appid": 1250250,
    "peak_count": 20
  },
  {
    "appid": 1250290,
    "peak_count": 1
  },
  {
    "appid": 1250300,
    "peak_count": -1
  },
  {
    "appid": 1250350,
    "peak_count": -1
  },
  {
    "appid": 1250410,
    "peak_count": 61775
  },
  {
    "appid": 1250440,
    "peak_count": 42
  },
  {
    "appid": 1250490,
    "peak_count": -1
  },
  {
    "appid": 1250510,
    "peak_count": -1
  },
  {
    "appid": 1250560,
    "peak_count": 73
  },
  {
    "appid": 1250590,
    "peak_count": -1
  },
  {
    "appid": 1250610,
    "peak_count": -1
  },
  {
    "appid": 1250640,
    "peak_count": -1
  },
  {
    "appid": 1250650,
    "peak_count": 588
  },
  {
    "appid": 1250660,
    "peak_count": -1
  },
  {
    "appid": 1250720,
    "peak_count": 1
  },
  {
    "appid": 1250760,
    "peak_count": 1041
  },
  {
    "appid": 1250770,
    "peak_count": -1
  },
  {
    "appid": 1250790,
    "peak_count": 586
  },
  {
    "appid": 1250810,
    "peak_count": -1
  },
  {
    "appid": 1250870,
    "peak_count": -1
  },
  {
    "appid": 1250900,
    "peak_count": -1
  },
  {
    "appid": 1250960,
    "peak_count": -1
  },
  {
    "appid": 1250990,
    "peak_count": 0
  },
  {
    "appid": 12510,
    "peak_count": -1
  },
  {
    "appid": 1251040,
    "peak_count": -1
  },
  {
    "appid": 1251060,
    "peak_count": -1
  },
  {
    "appid": 1251090,
    "peak_count": -1
  },
  {
    "appid": 1251200,
    "peak_count": -1
  },
  {
    "appid": 1251210,
    "peak_count": 257
  },
  {
    "appid": 1251250,
    "peak_count": -1
  },
  {
    "appid": 1251290,
    "peak_count": -1
  },
  {
    "appid": 1251300,
    "peak_count": 285
  },
  {
    "appid": 1251320,
    "peak_count": -1
  },
  {
    "appid": 1251330,
    "peak_count": 2
  },
  {
    "appid": 1251400,
    "peak_count": -1
  },
  {
    "appid": 1251410,
    "peak_count": 17
  },
  {
    "appid": 1251430,
    "peak_count": 2
  },
  {
    "appid": 1251460,
    "peak_count": 69
  },
  {
    "appid": 1251470,
    "peak_count": -1
  },
  {
    "appid": 1251530,
    "peak_count": -1
  },
  {
    "appid": 1251560,
    "peak_count": -1
  },
  {
    "appid": 1251690,
    "peak_count": 7
  },
  {
    "appid": 1251750,
    "peak_count": -1
  },
  {
    "appid": 1251760,
    "peak_count": 2
  },
  {
    "appid": 1251840,
    "peak_count": 4
  },
  {
    "appid": 1251850,
    "peak_count": 20
  },
  {
    "appid": 1251910,
    "peak_count": -1
  },
  {
    "appid": 1251930,
    "peak_count": 599
  },
  {
    "appid": 1251950,
    "peak_count": -1
  },
  {
    "appid": 1251970,
    "peak_count": 24
  },
  {
    "appid": 1251980,
    "peak_count": 13
  },
  {
    "appid": 12520,
    "peak_count": 37
  },
  {
    "appid": 1252000,
    "peak_count": 360
  },
  {
    "appid": 1252020,
    "peak_count": -1
  },
  {
    "appid": 1252030,
    "peak_count": -1
  },
  {
    "appid": 1252040,
    "peak_count": -1
  },
  {
    "appid": 1252050,
    "peak_count": -1
  },
  {
    "appid": 1252100,
    "peak_count": -1
  },
  {
    "appid": 1252120,
    "peak_count": -1
  },
  {
    "appid": 1252160,
    "peak_count": -1
  },
  {
    "appid": 1252190,
    "peak_count": -1
  },
  {
    "appid": 1252240,
    "peak_count": -1
  },
  {
    "appid": 1252250,
    "peak_count": -1
  },
  {
    "appid": 1252300,
    "peak_count": 84
  },
  {
    "appid": 1252330,
    "peak_count": 20050
  },
  {
    "appid": 1252390,
    "peak_count": -1
  },
  {
    "appid": 1252400,
    "peak_count": 19
  },
  {
    "appid": 1252410,
    "peak_count": 2
  },
  {
    "appid": 1252450,
    "peak_count": 1
  },
  {
    "appid": 1252480,
    "peak_count": 1
  },
  {
    "appid": 1252510,
    "peak_count": -1
  },
  {
    "appid": 1252560,
    "peak_count": 250
  },
  {
    "appid": 1252580,
    "peak_count": 13
  },
  {
    "appid": 1252600,
    "peak_count": 804
  },
  {
    "appid": 1252630,
    "peak_count": 2
  },
  {
    "appid": 1252650,
    "peak_count": -1
  },
  {
    "appid": 1252710,
    "peak_count": -1
  },
  {
    "appid": 1252730,
    "peak_count": -1
  },
  {
    "appid": 1252760,
    "peak_count": -1
  },
  {
    "appid": 1252780,
    "peak_count": 1166
  },
  {
    "appid": 1252830,
    "peak_count": 36
  },
  {
    "appid": 1252850,
    "peak_count": -1
  },
  {
    "appid": 1252920,
    "peak_count": -1
  },
  {
    "appid": 12530,
    "peak_count": -1
  },
  {
    "appid": 1253010,
    "peak_count": -1
  },
  {
    "appid": 1253050,
    "peak_count": -1
  },
  {
    "appid": 1253160,
    "peak_count": -1
  },
  {
    "appid": 1253180,
    "peak_count": -1
  },
  {
    "appid": 1253190,
    "peak_count": -1
  },
  {
    "appid": 1253240,
    "peak_count": -1
  },
  {
    "appid": 1253270,
    "peak_count": 10
  },
  {
    "appid": 1253320,
    "peak_count": 0
  },
  {
    "appid": 1253390,
    "peak_count": -1
  },
  {
    "appid": 1253400,
    "peak_count": -1
  },
  {
    "appid": 1253450,
    "peak_count": -1
  },
  {
    "appid": 1253520,
    "peak_count": -1
  },
  {
    "appid": 1253550,
    "peak_count": 26
  },
  {
    "appid": 1253580,
    "peak_count": 11
  },
  {
    "appid": 1253620,
    "peak_count": 1
  },
  {
    "appid": 1253650,
    "peak_count": -1
  },
  {
    "appid": 1253680,
    "peak_count": 15
  },
  {
    "appid": 1253690,
    "peak_count": 36
  },
  {
    "appid": 1253710,
    "peak_count": 550
  },
  {
    "appid": 1253720,
    "peak_count": -1
  },
  {
    "appid": 1253760,
    "peak_count": -1
  },
  {
    "appid": 1253860,
    "peak_count": 67
  },
  {
    "appid": 1253870,
    "peak_count": -1
  },
  {
    "appid": 1253920,
    "peak_count": 22811
  },
  {
    "appid": 1253930,
    "peak_count": -1
  },
  {
    "appid": 1253940,
    "peak_count": 4
  },
  {
    "appid": 1253950,
    "peak_count": 714
  },
  {
    "appid": 12540,
    "peak_count": 6
  },
  {
    "appid": 1254070,
    "peak_count": -1
  },
  {
    "appid": 1254110,
    "peak_count": -1
  },
  {
    "appid": 1254120,
    "peak_count": 76273
  },
  {
    "appid": 1254150,
    "peak_count": -1
  },
  {
    "appid": 1254160,
    "peak_count": -1
  },
  {
    "appid": 1254180,
    "peak_count": -1
  },
  {
    "appid": 1254200,
    "peak_count": -1
  },
  {
    "appid": 1254280,
    "peak_count": -1
  },
  {
    "appid": 1254360,
    "peak_count": 67
  },
  {
    "appid": 1254370,
    "peak_count": 234
  },
  {
    "appid": 1254390,
    "peak_count": -1
  },
  {
    "appid": 1254400,
    "peak_count": -1
  },
  {
    "appid": 1254410,
    "peak_count": -1
  },
  {
    "appid": 1254430,
    "peak_count": -1
  },
  {
    "appid": 1254480,
    "peak_count": -1
  },
  {
    "appid": 1254490,
    "peak_count": -1
  },
  {
    "appid": 1254590,
    "peak_count": -1
  },
  {
    "appid": 1254610,
    "peak_count": -1
  },
  {
    "appid": 1254620,
    "peak_count": 15
  },
  {
    "appid": 1254630,
    "peak_count": -1
  },
  {
    "appid": 1254670,
    "peak_count": -1
  },
  {
    "appid": 1254720,
    "peak_count": -1
  },
  {
    "appid": 1254820,
    "peak_count": -1
  },
  {
    "appid": 1254860,
    "peak_count": 5
  },
  {
    "appid": 1254870,
    "peak_count": 8
  },
  {
    "appid": 1254900,
    "peak_count": 344
  },
  {
    "appid": 1254930,
    "peak_count": -1
  },
  {
    "appid": 1255010,
    "peak_count": -1
  },
  {
    "appid": 1255030,
    "peak_count": 3
  },
  {
    "appid": 1255040,
    "peak_count": 5
  },
  {
    "appid": 1255050,
    "peak_count": -1
  },
  {
    "appid": 1255060,
    "peak_count": -1
  },
  {
    "appid": 1255130,
    "peak_count": -1
  },
  {
    "appid": 1255140,
    "peak_count": -1
  },
  {
    "appid": 1255160,
    "peak_count": 1
  },
  {
    "appid": 1255170,
    "peak_count": -1
  },
  {
    "appid": 1255230,
    "peak_count": -1
  },
  {
    "appid": 1255300,
    "peak_count": -1
  },
  {
    "appid": 1255380,
    "peak_count": 17
  },
  {
    "appid": 1255410,
    "peak_count": -1
  },
  {
    "appid": 1255420,
    "peak_count": -1
  },
  {
    "appid": 1255520,
    "peak_count": 157
  },
  {
    "appid": 1255550,
    "peak_count": 39
  },
  {
    "appid": 1255560,
    "peak_count": 472
  },
  {
    "appid": 1255630,
    "peak_count": 9535
  },
  {
    "appid": 1255640,
    "peak_count": -1
  },
  {
    "appid": 1255650,
    "peak_count": 662
  },
  {
    "appid": 1255660,
    "peak_count": -1
  },
  {
    "appid": 1255680,
    "peak_count": -1
  },
  {
    "appid": 1255730,
    "peak_count": -1
  },
  {
    "appid": 1255740,
    "peak_count": -1
  },
  {
    "appid": 1255810,
    "peak_count": -1
  },
  {
    "appid": 1255880,
    "peak_count": -1
  },
  {
    "appid": 1255910,
    "peak_count": -1
  },
  {
    "appid": 1255920,
    "peak_count": -1
  },
  {
    "appid": 1255970,
    "peak_count": -1
  },
  {
    "appid": 1255990,
    "peak_count": 10
  },
  {
    "appid": 12560,
    "peak_count": -1
  },
  {
    "appid": 1256040,
    "peak_count": -1
  },
  {
    "appid": 1256060,
    "peak_count": 44
  },
  {
    "appid": 1256130,
    "peak_count": -1
  },
  {
    "appid": 1256190,
    "peak_count": 1
  },
  {
    "appid": 1256220,
    "peak_count": -1
  },
  {
    "appid": 1256230,
    "peak_count": 288
  },
  {
    "appid": 1256350,
    "peak_count": -1
  },
  {
    "appid": 1256360,
    "peak_count": 1
  },
  {
    "appid": 1256380,
    "peak_count": -1
  },
  {
    "appid": 1256430,
    "peak_count": 3
  },
  {
    "appid": 1256440,
    "peak_count": -1
  },
  {
    "appid": 1256480,
    "peak_count": -1
  },
  {
    "appid": 1256490,
    "peak_count": -1
  },
  {
    "appid": 1256500,
    "peak_count": -1
  },
  {
    "appid": 1256510,
    "peak_count": -1
  },
  {
    "appid": 1256520,
    "peak_count": 4
  },
  {
    "appid": 1256530,
    "peak_count": -1
  },
  {
    "appid": 1256550,
    "peak_count": -1
  },
  {
    "appid": 1256610,
    "peak_count": 1255
  },
  {
    "appid": 1256650,
    "peak_count": 2
  },
  {
    "appid": 1256660,
    "peak_count": -1
  },
  {
    "appid": 1256670,
    "peak_count": 7211
  },
  {
    "appid": 1256680,
    "peak_count": -1
  },
  {
    "appid": 1256710,
    "peak_count": -1
  },
  {
    "appid": 1256770,
    "peak_count": -1
  },
  {
    "appid": 1256850,
    "peak_count": -1
  },
  {
    "appid": 1256870,
    "peak_count": 2
  },
  {
    "appid": 1256920,
    "peak_count": -1
  },
  {
    "appid": 1256980,
    "peak_count": -1
  },
  {
    "appid": 12570,
    "peak_count": 3
  },
  {
    "appid": 1257000,
    "peak_count": -1
  },
  {
    "appid": 1257190,
    "peak_count": -1
  },
  {
    "appid": 1257200,
    "peak_count": 296
  },
  {
    "appid": 1257210,
    "peak_count": -1
  },
  {
    "appid": 1257250,
    "peak_count": 1
  },
  {
    "appid": 1257270,
    "peak_count": 1
  },
  {
    "appid": 1257290,
    "peak_count": 3941
  },
  {
    "appid": 1257300,
    "peak_count": -1
  },
  {
    "appid": 1257310,
    "peak_count": 6
  },
  {
    "appid": 1257360,
    "peak_count": 677
  },
  {
    "appid": 1257410,
    "peak_count": -1
  },
  {
    "appid": 1257520,
    "peak_count": 1
  },
  {
    "appid": 1257540,
    "peak_count": -1
  },
  {
    "appid": 1257550,
    "peak_count": -1
  },
  {
    "appid": 1257560,
    "peak_count": -1
  },
  {
    "appid": 1257590,
    "peak_count": 1
  },
  {
    "appid": 1257600,
    "peak_count": -1
  },
  {
    "appid": 1257620,
    "peak_count": 2
  },
  {
    "appid": 1257660,
    "peak_count": -1
  },
  {
    "appid": 1257670,
    "peak_count": -1
  },
  {
    "appid": 1257700,
    "peak_count": -1
  },
  {
    "appid": 1257720,
    "peak_count": 1
  },
  {
    "appid": 1257810,
    "peak_count": 39
  },
  {
    "appid": 1257850,
    "peak_count": -1
  },
  {
    "appid": 1257860,
    "peak_count": -1
  },
  {
    "appid": 1257880,
    "peak_count": 39
  },
  {
    "appid": 1257890,
    "peak_count": -1
  },
  {
    "appid": 1257900,
    "peak_count": -1
  },
  {
    "appid": 1257910,
    "peak_count": -1
  },
  {
    "appid": 1257920,
    "peak_count": -1
  },
  {
    "appid": 1257930,
    "peak_count": -1
  },
  {
    "appid": 1257940,
    "peak_count": -1
  },
  {
    "appid": 1257950,
    "peak_count": -1
  },
  {
    "appid": 12580,
    "peak_count": 3
  },
  {
    "appid": 1258000,
    "peak_count": -1
  },
  {
    "appid": 1258020,
    "peak_count": -1
  },
  {
    "appid": 1258040,
    "peak_count": 132
  },
  {
    "appid": 1258070,
    "peak_count": -1
  },
  {
    "appid": 1258080,
    "peak_count": 7981
  },
  {
    "appid": 1258090,
    "peak_count": 4
  },
  {
    "appid": 1258200,
    "peak_count": 1
  },
  {
    "appid": 1258290,
    "peak_count": -1
  },
  {
    "appid": 1258310,
    "peak_count": -1
  },
  {
    "appid": 1258370,
    "peak_count": -1
  },
  {
    "appid": 1258410,
    "peak_count": -1
  },
  {
    "appid": 1258420,
    "peak_count": 1
  },
  {
    "appid": 1258440,
    "peak_count": -1
  },
  {
    "appid": 1258460,
    "peak_count": -1
  },
  {
    "appid": 1258480,
    "peak_count": -1
  },
  {
    "appid": 1258520,
    "peak_count": -1
  },
  {
    "appid": 1258560,
    "peak_count": -1
  },
  {
    "appid": 1258580,
    "peak_count": -1
  },
  {
    "appid": 1258590,
    "peak_count": 40
  },
  {
    "appid": 1258620,
    "peak_count": -1
  },
  {
    "appid": 1258640,
    "peak_count": -1
  },
  {
    "appid": 1258650,
    "peak_count": -1
  },
  {
    "appid": 1258730,
    "peak_count": -1
  },
  {
    "appid": 1258750,
    "peak_count": 1
  },
  {
    "appid": 1258770,
    "peak_count": -1
  },
  {
    "appid": 1258780,
    "peak_count": 1673
  },
  {
    "appid": 1258790,
    "peak_count": -1
  },
  {
    "appid": 1258800,
    "peak_count": -1
  },
  {
    "appid": 1258830,
    "peak_count": -1
  },
  {
    "appid": 1258840,
    "peak_count": -1
  },
  {
    "appid": 1258870,
    "peak_count": -1
  },
  {
    "appid": 1258900,
    "peak_count": -1
  },
  {
    "appid": 1258920,
    "peak_count": -1
  },
  {
    "appid": 1258950,
    "peak_count": -1
  },
  {
    "appid": 1258960,
    "peak_count": 2
  },
  {
    "appid": 1258980,
    "peak_count": 3
  },
  {
    "appid": 1258990,
    "peak_count": -1
  },
  {
    "appid": 12590,
    "peak_count": -1
  },
  {
    "appid": 1259000,
    "peak_count": -1
  },
  {
    "appid": 1259050,
    "peak_count": -1
  },
  {
    "appid": 1259130,
    "peak_count": -1
  },
  {
    "appid": 1259140,
    "peak_count": -1
  },
  {
    "appid": 1259150,
    "peak_count": -1
  },
  {
    "appid": 1259160,
    "peak_count": -1
  },
  {
    "appid": 1259180,
    "peak_count": -1
  },
  {
    "appid": 1259230,
    "peak_count": 26
  },
  {
    "appid": 1259280,
    "peak_count": -1
  },
  {
    "appid": 1259290,
    "peak_count": 1
  },
  {
    "appid": 1259300,
    "peak_count": 1
  },
  {
    "appid": 1259310,
    "peak_count": -1
  },
  {
    "appid": 1259330,
    "peak_count": -1
  },
  {
    "appid": 1259340,
    "peak_count": -1
  },
  {
    "appid": 1259370,
    "peak_count": -1
  },
  {
    "appid": 1259380,
    "peak_count": 17
  },
  {
    "appid": 1259390,
    "peak_count": 1
  },
  {
    "appid": 1259420,
    "peak_count": 27380
  },
  {
    "appid": 1259430,
    "peak_count": 48
  },
  {
    "appid": 1259460,
    "peak_count": 71
  },
  {
    "appid": 1259470,
    "peak_count": 1
  },
  {
    "appid": 1259480,
    "peak_count": 1
  },
  {
    "appid": 1259510,
    "peak_count": -1
  },
  {
    "appid": 1259520,
    "peak_count": 1
  },
  {
    "appid": 1259560,
    "peak_count": 191
  },
  {
    "appid": 1259570,
    "peak_count": -1
  },
  {
    "appid": 1259580,
    "peak_count": 4
  },
  {
    "appid": 1259600,
    "peak_count": 1
  },
  {
    "appid": 1259640,
    "peak_count": 100
  },
  {
    "appid": 1259660,
    "peak_count": -1
  },
  {
    "appid": 1259790,
    "peak_count": 602
  },
  {
    "appid": 1259800,
    "peak_count": 225
  },
  {
    "appid": 1259830,
    "peak_count": 1
  },
  {
    "appid": 1259840,
    "peak_count": 186
  },
  {
    "appid": 1259860,
    "peak_count": 2
  },
  {
    "appid": 1259890,
    "peak_count": -1
  },
  {
    "appid": 1259960,
    "peak_count": 3
  },
  {
    "appid": 1259970,
    "peak_count": 20674
  },
  {
    "appid": 1259980,
    "peak_count": 2867
  },
  {
    "appid": 1259990,
    "peak_count": 2
  },
  {
    "appid": 12600,
    "peak_count": 2
  },
  {
    "appid": 1260020,
    "peak_count": -1
  },
  {
    "appid": 1260030,
    "peak_count": -1
  },
  {
    "appid": 1260130,
    "peak_count": -1
  },
  {
    "appid": 1260160,
    "peak_count": 1
  },
  {
    "appid": 1260170,
    "peak_count": 1
  },
  {
    "appid": 1260230,
    "peak_count": -1
  },
  {
    "appid": 1260240,
    "peak_count": -1
  },
  {
    "appid": 1260250,
    "peak_count": -1
  },
  {
    "appid": 1260300,
    "peak_count": 2
  },
  {
    "appid": 1260310,
    "peak_count": -1
  },
  {
    "appid": 1260340,
    "peak_count": -1
  },
  {
    "appid": 1260370,
    "peak_count": 2
  },
  {
    "appid": 1260400,
    "peak_count": -1
  },
  {
    "appid": 1260470,
    "peak_count": -1
  },
  {
    "appid": 1260490,
    "peak_count": -1
  },
  {
    "appid": 1260520,
    "peak_count": 581
  },
  {
    "appid": 1260580,
    "peak_count": 3
  },
  {
    "appid": 1260590,
    "peak_count": 118
  },
  {
    "appid": 1260610,
    "peak_count": 1
  },
  {
    "appid": 1260690,
    "peak_count": -1
  },
  {
    "appid": 1260710,
    "peak_count": -1
  },
  {
    "appid": 1260720,
    "peak_count": -1
  },
  {
    "appid": 1260770,
    "peak_count": -1
  },
  {
    "appid": 1260800,
    "peak_count": 4
  },
  {
    "appid": 1260810,
    "peak_count": 494
  },
  {
    "appid": 1260830,
    "peak_count": -1
  },
  {
    "appid": 1260840,
    "peak_count": -1
  },
  {
    "appid": 1260860,
    "peak_count": -1
  },
  {
    "appid": 1260910,
    "peak_count": -1
  },
  {
    "appid": 1260920,
    "peak_count": -1
  },
  {
    "appid": 1260930,
    "peak_count": -1
  },
  {
    "appid": 1260960,
    "peak_count": 38
  },
  {
    "appid": 1261010,
    "peak_count": -1
  },
  {
    "appid": 1261020,
    "peak_count": -1
  },
  {
    "appid": 1261040,
    "peak_count": 741
  },
  {
    "appid": 1261060,
    "peak_count": 16
  },
  {
    "appid": 1261130,
    "peak_count": -1
  },
  {
    "appid": 1261160,
    "peak_count": -1
  },
  {
    "appid": 1261170,
    "peak_count": -1
  },
  {
    "appid": 1261180,
    "peak_count": 73
  },
  {
    "appid": 1261200,
    "peak_count": -1
  },
  {
    "appid": 1261280,
    "peak_count": -1
  },
  {
    "appid": 1261290,
    "peak_count": -1
  },
  {
    "appid": 1261300,
    "peak_count": 7
  },
  {
    "appid": 1261390,
    "peak_count": -1
  },
  {
    "appid": 1261490,
    "peak_count": -1
  },
  {
    "appid": 1261520,
    "peak_count": 108
  },
  {
    "appid": 1261530,
    "peak_count": -1
  },
  {
    "appid": 1261570,
    "peak_count": -1
  },
  {
    "appid": 1261630,
    "peak_count": -1
  },
  {
    "appid": 1261640,
    "peak_count": -1
  },
  {
    "appid": 1261650,
    "peak_count": -1
  },
  {
    "appid": 1261660,
    "peak_count": 4
  },
  {
    "appid": 1261670,
    "peak_count": 1
  },
  {
    "appid": 1261700,
    "peak_count": 3
  },
  {
    "appid": 1261750,
    "peak_count": -1
  },
  {
    "appid": 1261760,
    "peak_count": 8
  },
  {
    "appid": 1261790,
    "peak_count": -1
  },
  {
    "appid": 1261820,
    "peak_count": -1
  },
  {
    "appid": 1261880,
    "peak_count": -1
  },
  {
    "appid": 1261900,
    "peak_count": -1
  },
  {
    "appid": 1261960,
    "peak_count": -1
  },
  {
    "appid": 1261970,
    "peak_count": -1
  },
  {
    "appid": 1261980,
    "peak_count": -1
  },
  {
    "appid": 1261990,
    "peak_count": -1
  },
  {
    "appid": 1262030,
    "peak_count": 6
  },
  {
    "appid": 1262040,
    "peak_count": -1
  },
  {
    "appid": 1262070,
    "peak_count": 1
  },
  {
    "appid": 1262110,
    "peak_count": -1
  },
  {
    "appid": 1262140,
    "peak_count": -1
  },
  {
    "appid": 1262170,
    "peak_count": 15
  },
  {
    "appid": 1262180,
    "peak_count": -1
  },
  {
    "appid": 1262190,
    "peak_count": -1
  },
  {
    "appid": 1262240,
    "peak_count": 2276
  },
  {
    "appid": 1262260,
    "peak_count": -1
  },
  {
    "appid": 1262350,
    "peak_count": 862
  },
  {
    "appid": 1262380,
    "peak_count": -1
  },
  {
    "appid": 1262450,
    "peak_count": -1
  },
  {
    "appid": 1262460,
    "peak_count": 114
  },
  {
    "appid": 1262470,
    "peak_count": -1
  },
  {
    "appid": 1262500,
    "peak_count": -1
  },
  {
    "appid": 1262530,
    "peak_count": -1
  },
  {
    "appid": 1262540,
    "peak_count": 1220
  },
  {
    "appid": 1262560,
    "peak_count": 1934
  },
  {
    "appid": 1262580,
    "peak_count": 12152
  },
  {
    "appid": 1262600,
    "peak_count": 415
  },
  {
    "appid": 1262720,
    "peak_count": -1
  },
  {
    "appid": 1262760,
    "peak_count": 1
  },
  {
    "appid": 1262770,
    "peak_count": 2
  },
  {
    "appid": 1262780,
    "peak_count": 3
  },
  {
    "appid": 1262790,
    "peak_count": 0
  },
  {
    "appid": 1262830,
    "peak_count": -1
  },
  {
    "appid": 1262880,
    "peak_count": -1
  },
  {
    "appid": 1262890,
    "peak_count": -1
  },
  {
    "appid": 1262910,
    "peak_count": 73
  },
  {
    "appid": 1262920,
    "peak_count": -1
  },
  {
    "appid": 1262930,
    "peak_count": 65
  },
  {
    "appid": 1263060,
    "peak_count": -1
  },
  {
    "appid": 1263070,
    "peak_count": 292
  },
  {
    "appid": 1263090,
    "peak_count": -1
  },
  {
    "appid": 1263100,
    "peak_count": -1
  },
  {
    "appid": 1263110,
    "peak_count": -1
  },
  {
    "appid": 1263120,
    "peak_count": 1
  },
  {
    "appid": 1263200,
    "peak_count": -1
  },
  {
    "appid": 1263350,
    "peak_count": -1
  },
  {
    "appid": 1263370,
    "peak_count": 827
  },
  {
    "appid": 1263410,
    "peak_count": -1
  },
  {
    "appid": 1263450,
    "peak_count": 5
  },
  {
    "appid": 1263490,
    "peak_count": 5
  },
  {
    "appid": 1263510,
    "peak_count": -1
  },
  {
    "appid": 1263520,
    "peak_count": -1
  },
  {
    "appid": 1263530,
    "peak_count": 3
  },
  {
    "appid": 1263540,
    "peak_count": 4
  },
  {
    "appid": 1263550,
    "peak_count": 371
  },
  {
    "appid": 1263590,
    "peak_count": -1
  },
  {
    "appid": 1263610,
    "peak_count": -1
  },
  {
    "appid": 1263620,
    "peak_count": 80
  },
  {
    "appid": 1263680,
    "peak_count": -1
  },
  {
    "appid": 1263700,
    "peak_count": -1
  },
  {
    "appid": 1263720,
    "peak_count": -1
  },
  {
    "appid": 1263800,
    "peak_count": -1
  },
  {
    "appid": 1263820,
    "peak_count": 21
  },
  {
    "appid": 1263850,
    "peak_count": 93775
  },
  {
    "appid": 1263860,
    "peak_count": 1951
  },
  {
    "appid": 1263920,
    "peak_count": -1
  },
  {
    "appid": 1263990,
    "peak_count": -1
  },
  {
    "appid": 1264000,
    "peak_count": -1
  },
  {
    "appid": 1264010,
    "peak_count": -1
  },
  {
    "appid": 1264080,
    "peak_count": 0
  },
  {
    "appid": 1264090,
    "peak_count": -1
  },
  {
    "appid": 1264140,
    "peak_count": -1
  },
  {
    "appid": 1264160,
    "peak_count": 9
  },
  {
    "appid": 1264180,
    "peak_count": -1
  },
  {
    "appid": 1264220,
    "peak_count": -1
  },
  {
    "appid": 1264240,
    "peak_count": 1
  },
  {
    "appid": 1264250,
    "peak_count": 1273
  },
  {
    "appid": 1264280,
    "peak_count": 1012
  },
  {
    "appid": 1264290,
    "peak_count": 0
  },
  {
    "appid": 1264310,
    "peak_count": -1
  },
  {
    "appid": 1264350,
    "peak_count": 7
  },
  {
    "appid": 1264360,
    "peak_count": -1
  },
  {
    "appid": 1264410,
    "peak_count": -1
  },
  {
    "appid": 1264470,
    "peak_count": -1
  },
  {
    "appid": 1264500,
    "peak_count": 3
  },
  {
    "appid": 1264510,
    "peak_count": -1
  },
  {
    "appid": 1264520,
    "peak_count": 94
  },
  {
    "appid": 1264550,
    "peak_count": 1
  },
  {
    "appid": 1264630,
    "peak_count": -1
  },
  {
    "appid": 1264640,
    "peak_count": 11
  },
  {
    "appid": 1264650,
    "peak_count": -1
  },
  {
    "appid": 1264670,
    "peak_count": 4851
  },
  {
    "appid": 1264730,
    "peak_count": 2
  },
  {
    "appid": 1264740,
    "peak_count": 70
  },
  {
    "appid": 1264760,
    "peak_count": -1
  },
  {
    "appid": 1264770,
    "peak_count": -1
  },
  {
    "appid": 1264790,
    "peak_count": 13
  },
  {
    "appid": 1264800,
    "peak_count": -1
  },
  {
    "appid": 1264820,
    "peak_count": -1
  },
  {
    "appid": 1264850,
    "peak_count": -1
  },
  {
    "appid": 1264880,
    "peak_count": 31
  },
  {
    "appid": 1264890,
    "peak_count": -1
  },
  {
    "appid": 1264900,
    "peak_count": 2
  },
  {
    "appid": 1264920,
    "peak_count": -1
  },
  {
    "appid": 1264930,
    "peak_count": 4
  },
  {
    "appid": 1264970,
    "peak_count": 47
  },
  {
    "appid": 1264990,
    "peak_count": -1
  },
  {
    "appid": 1265030,
    "peak_count": -1
  },
  {
    "appid": 1265040,
    "peak_count": -1
  },
  {
    "appid": 1265070,
    "peak_count": -1
  },
  {
    "appid": 1265080,
    "peak_count": -1
  },
  {
    "appid": 1265110,
    "peak_count": -1
  },
  {
    "appid": 1265120,
    "peak_count": 5
  },
  {
    "appid": 1265130,
    "peak_count": -1
  },
  {
    "appid": 1265140,
    "peak_count": -1
  },
  {
    "appid": 1265200,
    "peak_count": -1
  },
  {
    "appid": 1265230,
    "peak_count": -1
  },
  {
    "appid": 1265240,
    "peak_count": 69
  },
  {
    "appid": 1265260,
    "peak_count": -1
  },
  {
    "appid": 1265270,
    "peak_count": -1
  },
  {
    "appid": 1265380,
    "peak_count": -1
  },
  {
    "appid": 1265390,
    "peak_count": -1
  },
  {
    "appid": 1265410,
    "peak_count": -1
  },
  {
    "appid": 1265440,
    "peak_count": -1
  },
  {
    "appid": 1265460,
    "peak_count": -1
  },
  {
    "appid": 1265510,
    "peak_count": 15
  },
  {
    "appid": 1265520,
    "peak_count": 3
  },
  {
    "appid": 1265570,
    "peak_count": 19
  },
  {
    "appid": 1265580,
    "peak_count": -1
  },
  {
    "appid": 1265650,
    "peak_count": -1
  },
  {
    "appid": 1265660,
    "peak_count": -1
  },
  {
    "appid": 1265680,
    "peak_count": 2
  },
  {
    "appid": 1265690,
    "peak_count": -1
  },
  {
    "appid": 1265720,
    "peak_count": -1
  },
  {
    "appid": 1265770,
    "peak_count": -1
  },
  {
    "appid": 1265810,
    "peak_count": 1
  },
  {
    "appid": 1265820,
    "peak_count": 1449
  },
  {
    "appid": 1265850,
    "peak_count": 21
  },
  {
    "appid": 1265860,
    "peak_count": 407
  },
  {
    "appid": 1265870,
    "peak_count": 16
  },
  {
    "appid": 1265920,
    "peak_count": 852
  },
  {
    "appid": 1265930,
    "peak_count": 346
  },
  {
    "appid": 1265960,
    "peak_count": -1
  },
  {
    "appid": 1265970,
    "peak_count": 4
  },
  {
    "appid": 1265990,
    "peak_count": 1
  },
  {
    "appid": 1266050,
    "peak_count": 1
  },
  {
    "appid": 1266070,
    "peak_count": -1
  },
  {
    "appid": 1266100,
    "peak_count": 213
  },
  {
    "appid": 1266120,
    "peak_count": -1
  },
  {
    "appid": 1266220,
    "peak_count": 247
  },
  {
    "appid": 1266260,
    "peak_count": 1
  },
  {
    "appid": 1266370,
    "peak_count": 6
  },
  {
    "appid": 1266380,
    "peak_count": -1
  },
  {
    "appid": 1266410,
    "peak_count": -1
  },
  {
    "appid": 1266420,
    "peak_count": -1
  },
  {
    "appid": 1266430,
    "peak_count": 216
  },
  {
    "appid": 1266440,
    "peak_count": -1
  },
  {
    "appid": 1266480,
    "peak_count": -1
  },
  {
    "appid": 1266560,
    "peak_count": 73
  },
  {
    "appid": 1266630,
    "peak_count": 1411
  },
  {
    "appid": 1266640,
    "peak_count": -1
  },
  {
    "appid": 1266650,
    "peak_count": -1
  },
  {
    "appid": 1266680,
    "peak_count": -1
  },
  {
    "appid": 1266690,
    "peak_count": 242
  },
  {
    "appid": 1266700,
    "peak_count": 2866
  },
  {
    "appid": 1266800,
    "peak_count": 388
  },
  {
    "appid": 1266820,
    "peak_count": -1
  },
  {
    "appid": 1266840,
    "peak_count": 2931
  },
  {
    "appid": 1266890,
    "peak_count": -1
  },
  {
    "appid": 1266900,
    "peak_count": -1
  },
  {
    "appid": 1266980,
    "peak_count": -1
  },
  {
    "appid": 12670,
    "peak_count": -1
  },
  {
    "appid": 1267040,
    "peak_count": -1
  },
  {
    "appid": 1267070,
    "peak_count": -1
  },
  {
    "appid": 1267130,
    "peak_count": -1
  },
  {
    "appid": 1267170,
    "peak_count": -1
  },
  {
    "appid": 1267230,
    "peak_count": -1
  },
  {
    "appid": 1267240,
    "peak_count": -1
  },
  {
    "appid": 1267260,
    "peak_count": 12
  },
  {
    "appid": 1267270,
    "peak_count": -1
  },
  {
    "appid": 1267310,
    "peak_count": -1
  },
  {
    "appid": 1267330,
    "peak_count": -1
  },
  {
    "appid": 1267370,
    "peak_count": -1
  },
  {
    "appid": 1267400,
    "peak_count": -1
  },
  {
    "appid": 1267410,
    "peak_count": -1
  },
  {
    "appid": 1267470,
    "peak_count": 3007
  },
  {
    "appid": 1267530,
    "peak_count": -1
  }
]